Workbook

Sheet README
A1: NTT DATA — Phase 1 Raw-Data Database | FY2015–FY2025
A2: SEARCH → VERIFY → EXTRACT → DOCUMENT → ORGANIZE. Raw reported data only; no DSO/DPO/DIO/CCC or final working-capital judgement.
A4: PROJECT SCOPE
A5: Research question | B5: How efficiently does NTT DATA convert operations and project work into cash compared with peers, where are the main working-capital inefficiencies/advantages, and what could improvement be worth financially?
A6: Current phase | B6: NTT DATA raw data only. Peer data and ratio/model calculations are intentionally excluded.
A7: Coverage | B7: FY2015–FY2025 inclusive. FY means the fiscal year ending March 31 of the succeeding calendar year.
A8: Currency / units | B8: JPY only. Core amount tables are mechanically standardized to ¥ million; no JPY→USD/EUR conversion.
A9: Accounting basis | B9: Main series: Japanese GAAP FY2015–FY2017; IFRS FY2018 onward.
A10: FY2017 bridge | B10: IFRS-restated FY2017 values are used only where needed for contract assets/liabilities and are explicitly flagged rather than mixed silently.
A11: FY2025 precision | B11: Retrieved FY2025 presentation reports many values in ¥bn to one decimal; these are mechanically multiplied by 1,000 to ¥mm and flagged as rounded.
A12: Missing data | B12: Missing cells use "N/A — Not disclosed" or "N/A — Insufficient public information to isolate reliably"; zero is never used as a placeholder.
A14: SOURCE HIERARCHY & DATA GOVERNANCE
A15: 1 | B15: Primary priority | C15: Audited annual/integrated reports, consolidated statements/notes, official data tables, Kessan Tanshin, statutory/business reports and earnings presentations.
A16: 2 | B16: Traceability | C16: Every wide time-series row has a fiscal-year source-ID matrix. The Sources sheet maps each ID to document, status and URL.
A17: 3 | B17: No silent assumptions | C17: Definition changes, restatements, combined accounts, acquisitions, reorganizations and missing disclosures are recorded in Assumptions & Limitations.
A18: 4 | B18: No ratios yet | C18: No DSO, DPO, DIO, CCC, current/quick ratio, OWC/revenue, CFO/EBITDA, FCF margin, peer median or implied cash-release calculation is included.
A20: DATASET READINESS — PHASE 1
A21: Core income statement | B21: Strong | C21: FY2015–FY2025 captured; FY2025 is presentation-rounded.
A22: Core balance sheet | B22: Strong | C22: FY2015–FY2024 detailed; FY2025 captured at presentation level with reposted-definition warnings.
A23: Working capital | B23: Strong FY2018–FY2024; partial at edges | C23: Contract balances become clean under IFRS. FY2025 separate AR/contract-asset and pure trade-payables breakdowns remain incomplete.
A24: Cash flow | B24: Strong FY2015–FY2024; FY2025 gap | C24: Full FY2025 CFO/CFI/CFF detail was not reliably extracted in this research pass.
A25: Orders & backlog | B25: Strong | C25: Annual series captured for all target years.
A26: Segments / service mix | B26: Moderate | C26: Recent current-structure detail plus historical overseas KPI captured; historical labels are not force-mapped.
A27: Structural changes | B27: Strong | C27: Dell Services, accounting transition, NTT Ltd. combination, three-company structure, data-center transactions and 2025 delisting documented.
A29: RECOMMENDED MODELLING WINDOW LATER
A30: Retain FY2015–FY2025 in the database for historical context, but use FY2018–FY2025 as the primary accounting-comparable window because it is IFRS-based. Treat FY2022 as a major structural break caused by the NTT Ltd. business combination; for cleaner operational comparisons, consider FY2018–FY2021 versus FY2023–FY2025. Lease-sensitive analysis should also flag the IFRS 16-era presentation from FY2019.

Sheet NTT DATA Financials
A1: NTT DATA Financials — Raw Reported Data
A2: Core statements in ¥ million. Source IDs are attached by fiscal year; accounting and structural breaks are not normalized away.
A3: Metric metadata | D3: Reported values | O3: Source ID by fiscal year | Z3: Comparability / precision
A4: Metric | B4: Unit | C4: Definition / note | D4: FY2015 | E4: FY2016 | F4: FY2017 | G4: FY2018 | H4: FY2019 | I4: FY2020 | J4: FY2021 | K4: FY2022 | L4: FY2023 | M4: FY2024 | N4: FY2025 | O4: FY2015 | P4: FY2016 | Q4: FY2017 | R4: FY2018 | S4: FY2019 | T4: FY2020 | U4: FY2021 | V4: FY2022 | W4: FY2023 | X4: FY2024 | Y4: FY2025 | Z4: Comparability / precision
A5: INCOME STATEMENT
A6: Revenue / net sales | B6: ¥ million | C6: Reported consolidated revenue / net sales. | D6: 1614897 | E6: 1732473 | F6: 2117167 | G6: 2163625 | H6: 2266808 | I6: 2318658 | J6: 2551906 | K6: 3490182 | L6: 4367387 | M6: 4638721 | N6: 5004600 | O6: S02 | P6: S03 | Q6: S03 | R6: S05 | S6: S06 | T6: S07 | U6: S08 | V6: S09 | W6: S10 | X6: S11 | Y6: S13 | Z6: FY2015–FY2017 JGAAP; FY2018+ IFRS. FY2025 from ¥5,004.6bn presentation.
A7: Cost of sales / cost of revenue | B7: ¥ million | C7: Reported cost of sales. | D7: 1216795 | E7: 1293600 | F7: 1592745 | G7: 1618636 | H7: 1694577 | I7: 1734083 | J7: 1875904 | K7: 2567948 | L7: 3172421 | M7: 3351333 | N7: 3522200 | O7: S02 | P7: S03 | Q7: S03 | R7: S05 | S7: S06 | T7: S07 | U7: S08 | V7: S09 | W7: S10 | X7: S11 | Y7: S13 | Z7: FY2025 rounded.
A8: Gross profit | B8: ¥ million | C8: Reported gross profit. | D8: 398101 | E8: 438872 | F8: 524421 | G8: 544988 | H8: 572231 | I8: 584575 | J8: 676002 | K8: 922234 | L8: 1194966 | M8: 1287388 | N8: 1482500 | O8: S02 | P8: S03 | Q8: S03 | R8: S05 | S8: S06 | T8: S07 | U8: S08 | V8: S09 | W8: S10 | X8: S11 | Y8: S13 | Z8: FY2025 rounded.
A9: Selling, general & administrative expenses | B9: ¥ million | C9: Reported SG&A. | D9: 297216 | E9: 321763 | F9: 400899 | G9: 397272 | H9: 441294 | I9: 445402 | J9: 463411 | K9: 663124 | L9: 885416 | M9: 963525 | N9: 994200 | O9: S02 | P9: S03 | Q9: S03 | R9: S05 | S9: S06 | T9: S07 | U9: S08 | V9: S09 | W9: S10 | X9: S11 | Y9: S13 | Z9: FY2025 rounded.
A10: Operating profit / operating income | B10: ¥ million | C10: JGAAP operating income through FY2017; IFRS operating profit thereafter. | D10: 100885 | E10: 117109 | F10: 123522 | G10: 147716 | H10: 130937 | I10: 139173 | J10: 212590 | K10: 259110 | L10: 309551 | M10: 323862 | N10: 488200 | O10: S02 | P10: S03 | Q10: S03 | R10: S05 | S10: S06 | T10: S07 | U10: S08 | V10: S09 | W10: S10 | X10: S11 | Y10: S13 | Z10: FY2025 includes material data-center transfer/disposal gain effects discussed by management.
A11: EBITDA — officially reported KPI | B11: ¥ million | C11: Official company EBITDA KPI; not an analyst reconstruction. | D11: 272162 | E11: 297199 | F11: 313706 | G11: 308400 | H11: 295700 | I11: 320300 | J11: 394900 | K11: 482200 | L11: 591400 | M11: 622500 | N11: 803700 | O11: S03 | P11: S03 | Q11: S03 | R11: S04 | S11: S04 | T11: S04 | U11: S04 | V11: S04 | W11: S04 | X11: S13 | Y11: S13 | Z11: Definition may evolve. FY2018+ historical values from official tables; FY2024/FY2025 rounded in company materials.
A12: Profit before tax / income before income taxes | B12: ¥ million | C12: Reported pre-tax profit. | D12: 107789 | E12: 105332 | F12: 100083 | G12: 146914 | H12: 120155 | I12: 130452 | J12: 215849 | K12: 242800 | L12: 248602 | M12: 249006 | N12: 406500 | O12: S02 | P12: S03 | Q12: S03 | R12: S05 | S12: S06 | T12: S07 | U12: S08 | V12: S09 | W12: S10 | X12: S11 | Y12: S13 | Z12: FY2025 rounded.
A13: Income tax expense | B13: ¥ million | C13: Reported tax expense. | D13: 42354 | E13: 36820 | F13: 38716 | G13: 49210 | H13: 40383 | I13: 48751 | J13: 65747 | K13: 75929 | L13: 103062 | M13: 109746 | N13: 141400 | O13: S02 | P13: S03 | Q13: S03 | R13: S05 | S13: S06 | T13: S07 | U13: S08 | V13: S09 | W13: S10 | X13: S11 | Y13: S13 | Z13: FY2025 rounded.
A14: Net income / profit for the year | B14: ¥ million | C14: Consolidated net income / IFRS profit. | D14: 65434 | E14: 68512 | F14: 61367 | G14: 97704 | H14: 79772 | I14: 81701 | J14: 150102 | K14: 166871 | L14: 145541 | M14: 139260 | N14: 265100 | O14: S02 | P14: S03 | Q14: S03 | R14: S05 | S14: S06 | T14: S07 | U14: S08 | V14: S09 | W14: S10 | X14: S11 | Y14: S13 | Z14: FY2025 rounded.
A15: Profit attributable to owners of parent / NTT DATA shareholders | B15: ¥ million | C15: Parent-owner profit. | D15: 63373 | E15: 65686 | F15: 58173 | G15: 93616 | H15: 75148 | I15: 76843 | J15: 142979 | K15: 149962 | L15: 133869 | M15: 142454 | N15: 201400 | O15: S02 | P15: S03 | Q15: S03 | R15: S05 | S15: S06 | T15: S07 | U15: S08 | V15: S09 | W15: S10 | X15: S11 | Y15: S13 | Z15: FY2025 rounded.
A16: Finance / interest income | B16: ¥ million | C16: JGAAP interest income through FY2017; IFRS finance income thereafter. | D16: 1256 | E16: 1507 | F16: 2209 | G16: 6848 | H16: 6026 | I16: 6661 | J16: 9665 | K16: 16388 | L16: 26847 | M16: 29586 | N16: N/A — Not disclosed | O16: S02 | P16: S03 | Q16: S03 | R16: S05 | S16: S06 | T16: S07 | U16: S08 | V16: S09 | W16: S10 | X16: S11 | Z16: FY2025 retrieved presentation shows combined net finance/equity-method line, not separate finance income.
A17: Finance costs / interest expense | B17: ¥ million | C17: JGAAP interest expense through FY2017; IFRS finance costs thereafter. | D17: 5492 | E17: 5372 | F17: 6051 | G17: 7825 | H17: 17117 | I17: 9083 | J17: 6201 | K17: 33102 | L17: 88100 | M17: 105838 | N17: N/A — Not disclosed | O17: S02 | P17: S03 | Q17: S03 | R17: S05 | S17: S06 | T17: S07 | U17: S08 | V17: S09 | W17: S10 | X17: S11 | Z17: FY2025 separate finance costs not isolated in retrieved presentation.
A18: Finance income + costs + equity-method result, net | B18: ¥ million | C18: Presentation line retained where separate components are unavailable. | D18: N/A — Not disclosed | E18: N/A — Not disclosed | F18: N/A — Not disclosed | G18: N/A — Not disclosed | H18: N/A — Not disclosed | I18: N/A — Not disclosed | J18: N/A — Not disclosed | K18: N/A — Not disclosed | L18: N/A — Not disclosed | M18: N/A — Not disclosed | N18: -81700 | Y18: S13 | Z18: FY2025 only; not comparable to finance-cost row.
A19: BALANCE SHEET / STATEMENT OF FINANCIAL POSITION
A20: Cash and cash equivalents | B20: ¥ million | C20: FY2015–FY2017 from CFS ending cash equivalents; IFRS years from statement of financial position. | D20: 233553 | E20: 260038 | F20: 190070 | G20: 251309 | H20: 205356 | I20: 287058 | J20: 246941 | K20: 415359 | L20: 431774 | M20: 444635 | N20: 384900 | O20: S02 | P20: S03 | Q20: S03 | R20: S05 | S20: S06 | T20: S07 | U20: S08 | V20: S09 | W20: S10 | X20: S11 | Y20: S13 | Z20: JGAAP balance-sheet 'cash and deposits' differs from cash-equivalent definition.
A21: Cash and deposits — JGAAP balance-sheet caption | B21: ¥ million | C21: JGAAP balance-sheet caption; not used as primary cross-period cash row. | D21: 148495 | E21: 212459 | F21: 186616 | G21: N/A — Not disclosed | H21: N/A — Not disclosed | I21: N/A — Not disclosed | J21: N/A — Not disclosed | K21: N/A — Not disclosed | L21: N/A — Not disclosed | M21: N/A — Not disclosed | N21: N/A — Not disclosed | O21: S02 | P21: S03 | Q21: S03 | Z21: Not directly comparable to IFRS cash-and-cash-equivalents caption.
A22: Total current assets | B22: ¥ million | C22: Reported total current assets. | D22: 842701 | E22: 897910 | F22: 885425 | G22: 974467 | H22: 966890 | I22: 1110056 | J22: 1247041 | K22: 2248950 | L22: 2432955 | M22: 2754729 | N22: 2859500 | O22: S02 | P22: S03 | Q22: S03 | R22: S05 | S22: S06 | T22: S07 | U22: S08 | V22: S09 | W22: S10 | X22: S11 | Y22: S13 | Z22: FY2025 rounded.
A23: Total current liabilities | B23: ¥ million | C23: Reported total current liabilities. | D23: 537258 | E23: 833619 | F23: 665971 | G23: 816859 | H23: 883038 | I23: 924387 | J23: 987797 | K23: 1804303 | L23: 2513881 | M23: 2833056 | N23: 2755100 | O23: S02 | P23: S03 | Q23: S03 | R23: S05 | S23: S06 | T23: S07 | U23: S08 | V23: S09 | W23: S10 | X23: S11 | Y23: S13 | Z23: FY2025 rounded.
A24: Total assets | B24: ¥ million | C24: Reported total assets. | D24: 1860319 | E24: 2238941 | F24: 2234277 | G24: 2476062 | H24: 2686008 | I24: 2897015 | J24: 3084513 | K24: 6158194 | L24: 7219429 | M24: 7777384 | N24: 8622900 | O24: S02 | P24: S03 | Q24: S03 | R24: S05 | S24: S06 | T24: S07 | U24: S08 | V24: S09 | W24: S10 | X24: S11 | Y24: S13 | Z24: FY2022 step-change reflects NTT Ltd. combination; FY2025 rounded.
A25: Total liabilities | B25: ¥ million | C25: Reported total liabilities. | D25: 1086648 | E25: 1405225 | F25: 1365414 | G25: 1509253 | H25: 1698593 | I25: 1770468 | J25: 1756246 | K25: 3761829 | L25: 4439015 | M25: 4908892 | N25: 5313100 | O25: S02 | P25: S03 | Q25: S03 | R25: S05 | S25: S06 | T25: S07 | U25: S08 | V25: S09 | W25: S10 | X25: S11 | Y25: S13 | Z25: FY2022 step-change reflects NTT Ltd. combination; FY2025 rounded.
A26: Total equity / net assets | B26: ¥ million | C26: JGAAP net assets through FY2017; IFRS total equity thereafter. | D26: 773670 | E26: 833715 | F26: 868863 | G26: 966809 | H26: 987415 | I26: 1126548 | J26: 1328267 | K26: 2396365 | L26: 2780414 | M26: 2868492 | N26: 3309800 | O26: S02 | P26: S03 | Q26: S03 | R26: S05 | S26: S06 | T26: S07 | U26: S08 | V26: S09 | W26: S10 | X26: S11 | Y26: S13 | Z26: Caption changes with framework; FY2025 rounded.
A27: Equity attributable to owners / NTT DATA shareholders | B27: ¥ million | C27: Owner-attributable equity. | D27: 740908 | E27: 802148 | F27: 833858 | G27: 925667 | H27: 939683 | I27: 1072899 | J27: 1270874 | K27: 1452367 | L27: 1719204 | M27: 1830461 | N27: 2139600 | O27: S02 | P27: S03 | Q27: S03 | R27: S05 | S27: S06 | T27: S07 | U27: S08 | V27: S09 | W27: S10 | X27: S11 | Y27: S13 | Z27: FY2025 rounded.
A28: Short-term borrowings / short-term loans payable | B28: ¥ million | C28: JGAAP short-term loans payable; IFRS pure short-term borrowing not isolated in retrieved summary statements. | D28: 51627 | E28: 213160 | F28: 46846 | G28: N/A — Insufficient public information to isolate reliably | H28: N/A — Insufficient public information to isolate reliably | I28: N/A — Insufficient public information to isolate reliably | J28: N/A — Insufficient public information to isolate reliably | K28: N/A — Insufficient public information to isolate reliably | L28: N/A — Insufficient public information to isolate reliably | M28: N/A — Insufficient public information to isolate reliably | N28: N/A — Insufficient public information to isolate reliably | O28: S02 | P28: S03 | Q28: S03 | Z28: Do not substitute IFRS current 'bonds and borrowings' for pure short-term borrowing.
A29: Current portion of long-term debt | B29: ¥ million | C29: JGAAP current portion of long-term loans payable. | D29: 29245 | E29: 53461 | F29: 567 | G29: N/A — Insufficient public information to isolate reliably | H29: N/A — Insufficient public information to isolate reliably | I29: N/A — Insufficient public information to isolate reliably | J29: N/A — Insufficient public information to isolate reliably | K29: N/A — Insufficient public information to isolate reliably | L29: N/A — Insufficient public information to isolate reliably | M29: N/A — Insufficient public information to isolate reliably | N29: N/A — Insufficient public information to isolate reliably | O29: S02 | P29: S03 | Q29: S03 | Z29: IFRS presentation aggregates current bonds and borrowings.
A30: Current bonds and borrowings / current debt aggregate | B30: ¥ million | C30: IFRS current bonds & borrowings. | D30: N/A — Not disclosed | E30: N/A — Not disclosed | F30: N/A — Not disclosed | G30: 134586 | H30: 157094 | I30: 105748 | J30: 102829 | K30: 278843 | L30: 755830 | M30: 969666 | N30: 732300 | R30: S05 | S30: S06 | T30: S07 | U30: S08 | V30: S09 | W30: S10 | X30: S11 | Y30: S13 | Z30: FY2025 rounded.
A31: Long-term borrowings — JGAAP | B31: ¥ million | C31: JGAAP long-term loans payable. | D31: 109451 | E31: 168618 | F31: 358779 | G31: N/A — Not disclosed | H31: N/A — Not disclosed | I31: N/A — Not disclosed | J31: N/A — Not disclosed | K31: N/A — Not disclosed | L31: N/A — Not disclosed | M31: N/A — Not disclosed | N31: N/A — Not disclosed | O31: S02 | P31: S03 | Q31: S03 | Z31: IFRS aggregates bonds and borrowings.
A32: Bonds — non-current JGAAP | B32: ¥ million | C32: JGAAP non-current bonds payable. | D32: 210062 | E32: 160075 | F32: 110081 | G32: N/A — Not disclosed | H32: N/A — Not disclosed | I32: N/A — Not disclosed | J32: N/A — Not disclosed | K32: N/A — Not disclosed | L32: N/A — Not disclosed | M32: N/A — Not disclosed | N32: N/A — Not disclosed | O32: S02 | P32: S03 | Q32: S03 | Z32: Separate from long-term loans under JGAAP.
A33: Bonds and borrowings — non-current IFRS | B33: ¥ million | C33: IFRS non-current bonds and borrowings. | D33: N/A — Not disclosed | E33: N/A — Not disclosed | F33: N/A — Not disclosed | G33: 446437 | H33: 440861 | I33: 473154 | J33: 393651 | K33: 1453018 | L33: 1419483 | M33: 1629411 | N33: 2102800 | R33: S05 | S33: S06 | T33: S07 | U33: S08 | V33: S09 | W33: S10 | X33: S11 | Y33: S13 | Z33: FY2025 rounded.
A34: Lease liabilities — current | B34: ¥ million | C34: Separately reported IFRS lease liabilities where retrieved. | D34: N/A — Not disclosed | E34: N/A — Not disclosed | F34: N/A — Not disclosed | G34: N/A — Not disclosed | H34: 39143 | I34: 41439 | J34: 42560 | K34: 64280 | L34: 70096 | M34: 70418 | N34: N/A — Not disclosed | S34: S06 | T34: S07 | U34: S08 | V34: S09 | W34: S10 | X34: S11 | Z34: IFRS 16-era presentation visible from FY2019; FY2025 current lease amount not isolated in retrieved presentation.
A35: Lease liabilities — non-current | B35: ¥ million | C35: Separately reported IFRS lease liabilities where retrieved. | D35: N/A — Not disclosed | E35: N/A — Not disclosed | F35: N/A — Not disclosed | G35: N/A — Not disclosed | H35: 122219 | I35: 117866 | J35: 124004 | K35: 204640 | L35: 206105 | M35: 168280 | N35: 174000 | S35: S06 | T35: S07 | U35: S08 | V35: S09 | W35: S10 | X35: S11 | Y35: S13 | Z35: FY2025 rounded.
A36: Interest-bearing debt — official KPI where directly reported | B36: ¥ million | C36: Company KPI, not calculated from components. | D36: 400387 | E36: 650814 | F36: 592003 | G36: 605000 | H36: 598000 | I36: 578900 | J36: 496500 | K36: N/A — Not disclosed | L36: N/A — Not disclosed | M36: 2599100 | N36: 2835100 | O36: S03 | P36: S03 | Q36: S03 | R36: S04 | S36: S04 | T36: S04 | U36: S04 | X36: S13 | Y36: S13 | Z36: Some years unavailable as a directly reported KPI in retrieved sources; latest presentation definition excludes leases.
A37: Goodwill | B37: ¥ million | C37: Reported goodwill. | D37: 168879 | E37: N/A — Not disclosed | F37: N/A — Not disclosed | G37: 357014 | H37: 391017 | I37: 415272 | J37: 493769 | K37: 1133559 | L37: 1321773 | M37: 1351114 | N37: 1492700 | O37: S02 | R37: S05 | S37: S06 | T37: S07 | U37: S08 | V37: S09 | W37: S10 | X37: S11 | Y37: S13 | Z37: FY2022 step-change reflects combination; FY2025 rounded.
A38: Intangible assets | B38: ¥ million | C38: Reported intangible assets. | D38: 535337 | E38: N/A — Not disclosed | F38: N/A — Not disclosed | G38: 444444 | H38: 477716 | I38: 477495 | J38: 506705 | K38: 653205 | L38: 693716 | M38: 694725 | N38: 707900 | O38: S02 | R38: S05 | S38: S06 | T38: S07 | U38: S08 | V38: S09 | W38: S10 | X38: S11 | Y38: S13 | Z38: FY2015 JGAAP caption not perfectly comparable; FY2025 rounded.
A39: Property, plant & equipment | B39: ¥ million | C39: Reported PP&E; ROU assets are not added. | D39: 302575 | E39: 356860 | F39: 380350 | G39: 355717 | H39: 344922 | I39: 339158 | J39: 332225 | K39: 1372468 | L39: 1914447 | M39: 2178203 | N39: 2644600 | O39: S02 | P39: S03 | Q39: S03 | R39: S05 | S39: S06 | T39: S07 | U39: S08 | V39: S09 | W39: S10 | X39: S11 | Y39: S13 | Z39: FY2022+ major data-center asset expansion; FY2025 rounded.

Sheet Working Capital
A1: NTT DATA Working Capital — Raw Balances
A2: Receivables, contract assets, inventory, payables and contract liabilities remain separate. Combined captions are never silently treated as pure trade balances.
A3: Metric metadata | D3: Reported values | O3: Source ID by fiscal year | Z3: Comparability / precision
A4: Metric | B4: Unit | C4: Definition / note | D4: FY2015 | E4: FY2016 | F4: FY2017 | G4: FY2018 | H4: FY2019 | I4: FY2020 | J4: FY2021 | K4: FY2022 | L4: FY2023 | M4: FY2024 | N4: FY2025 | O4: FY2015 | P4: FY2016 | Q4: FY2017 | R4: FY2018 | S4: FY2019 | T4: FY2020 | U4: FY2021 | V4: FY2022 | W4: FY2023 | X4: FY2024 | Y4: FY2025 | Z4: Comparability / precision
A5: RECEIVABLES
A6: Trade receivables / notes & accounts receivable — trade | B6: ¥ million | C6: Pure trade receivable balance where separately isolated. | D6: 403146 | E6: 458085 | F6: 504632 | G6: 489398 | H6: 502994 | I6: 517393 | J6: 581302 | K6: 1088978 | L6: 1261976 | M6: N/A — Insufficient public information to isolate reliably | N6: N/A — Insufficient public information to isolate reliably | O6: S02 | P6: S03 | Q6: S03 | R6: S05 | S6: S06 | T6: S07 | U6: S08 | V6: S12 | W6: S12 | X6: S20 | Y6: S13 | Z6: FY2024 combined balance is available but pure trade component not isolated in retrieved notes; FY2025 presentation combines receivables and contract assets.
A7: Accounts receivable — other | B7: ¥ million | C7: IFRS note component of trade and other receivables. | D7: N/A — Not disclosed | E7: N/A — Not disclosed | F7: N/A — Not disclosed | G7: 43708 | H7: 54852 | I7: 65772 | J7: 52731 | K7: 88711 | L7: 70229 | M7: N/A — Insufficient public information to isolate reliably | N7: N/A — Insufficient public information to isolate reliably | R7: S05 | S7: S06 | T7: S07 | U7: S08 | V7: S12 | W7: S12 | Z7: Kept separate from trade AR.
A8: Other within trade & other receivables | B8: ¥ million | C8: Other receivable component where separately disclosed. | D8: N/A — Not disclosed | E8: N/A — Not disclosed | F8: N/A — Not disclosed | G8: 16020 | H8: 14329 | I8: 18718 | J8: 38632 | K8: 64581 | L8: 64191 | M8: N/A — Insufficient public information to isolate reliably | N8: N/A — Insufficient public information to isolate reliably | R8: S05 | S8: S06 | T8: S07 | U8: S08 | V8: S12 | W8: S12 | Z8: Kept separate from trade AR.
A9: Trade and other receivables — combined balance | B9: ¥ million | C9: Published IFRS combined balance. | D9: N/A — Not disclosed | E9: N/A — Not disclosed | F9: N/A — Not disclosed | G9: 549126 | H9: 572175 | I9: 601883 | J9: 672665 | K9: 1242269 | L9: 1396396 | M9: 1535492 | N9: N/A — Insufficient public information to isolate reliably | R9: S05 | S9: S06 | T9: S07 | U9: S08 | V9: S12 | W9: S12 | X9: S11 | Z9: Do not use as pure trade AR without a consistent methodology.
A10: Receivables + contract assets — FY2025 reposted presentation caption | B10: ¥ million | C10: Presentation caption explicitly marked as a reposted breakdown. | D10: N/A — Not disclosed | E10: N/A — Not disclosed | F10: N/A — Not disclosed | G10: N/A — Not disclosed | H10: N/A — Not disclosed | I10: N/A — Not disclosed | J10: N/A — Not disclosed | K10: N/A — Not disclosed | L10: N/A — Not disclosed | M10: 1587700 | N10: 1806000 | X10: S13 | Y10: S13 | Z10: FY2024 reposted comparison does not reconcile to audited FY2024 trade/other receivables + contract assets; preserved separately.
A11: Allowance for doubtful accounts — JGAAP | B11: ¥ million | C11: JGAAP contra-receivable allowance. | D11: -2614 | E11: -3740 | F11: -3217 | G11: N/A — Insufficient public information to isolate reliably | H11: N/A — Insufficient public information to isolate reliably | I11: N/A — Insufficient public information to isolate reliably | J11: N/A — Insufficient public information to isolate reliably | K11: N/A — Insufficient public information to isolate reliably | L11: N/A — Insufficient public information to isolate reliably | M11: N/A — Insufficient public information to isolate reliably | N11: N/A — Insufficient public information to isolate reliably | O11: S02 | P11: S03 | Q11: S03 | Z11: IFRS ECL allowance is not filled without a clean like-for-like extraction.
A12: CONTRACT ASSETS
A13: Contract assets — closing balance | B13: ¥ million | C13: IFRS contract assets; FY2017 is an IFRS-restated bridge value. | D13: N/A — Not disclosed | E13: N/A — Not disclosed | F13: 81948 | G13: 81929 | H13: 74828 | I13: 101496 | J13: 105477 | K13: 123008 | L13: 150738 | M13: 197069 | N13: N/A — Insufficient public information to isolate reliably | Q13: S05 | R13: S05 | S13: S06 | T13: S07 | U13: S08 | V13: S12 | W13: S12 | X13: S20 | Z13: FY2017 IFRS-restated; FY2025 separate balance not isolated.
A14: Contract asset definition | B14: text | C14: System-development consideration in progress; reclassified to trade receivables when payment right becomes unconditional. | G14: See note | H14: See note | I14: See note | J14: See note | K14: See note | L14: See note | M14: See note | N14: See note | R14: S05 | S14: S06 | T14: S07 | U14: S08 | V14: S12 | W14: S12 | X14: S20 | Y14: S13 | Z14: Accounting-policy evidence; not a numerical series.
A15: INVENTORIES
A16: Inventories — total | B16: ¥ million | C16: Reported total inventory. | D16: 26676 | E16: 31211 | F16: 41165 | G16: 15294 | H16: 13727 | I16: 14476 | J16: 25429 | K16: 76221 | L16: 51243 | M16: 55900 | N16: 69100 | O16: S02 | P16: S03 | Q16: S03 | R16: S05 | S16: S06 | T16: S07 | U16: S08 | V16: S12 | W16: S12 | X16: S20 | Y16: S13 | Z16: FY2022 step-up coincides with NTT Ltd. consolidation; FY2025 rounded.
A17: Merchandise / finished goods | B17: ¥ million | C17: Inventory component where retrieved. | D17: N/A — Not disclosed | E17: N/A — Not disclosed | F17: N/A — Not disclosed | G17: N/A — Not disclosed | H17: N/A — Not disclosed | I17: N/A — Not disclosed | J17: N/A — Not disclosed | K17: 55205 | L17: 33081 | M17: N/A — Not disclosed | N17: N/A — Not disclosed | V17: S12 | W17: S12 | Z17: Detailed components captured for FY2022–FY2023 only.
A18: Work in progress | B18: ¥ million | C18: Inventory component where retrieved. | D18: N/A — Not disclosed | E18: N/A — Not disclosed | F18: N/A — Not disclosed | G18: N/A — Not disclosed | H18: N/A — Not disclosed | I18: N/A — Not disclosed | J18: N/A — Not disclosed | K18: 17165 | L18: 15753 | M18: N/A — Not disclosed | N18: N/A — Not disclosed | V18: S12 | W18: S12 | Z18: Detailed components captured for FY2022–FY2023 only.
A19: Raw materials / supplies | B19: ¥ million | C19: Inventory component where retrieved. | D19: N/A — Not disclosed | E19: N/A — Not disclosed | F19: N/A — Not disclosed | G19: N/A — Not disclosed | H19: N/A — Not disclosed | I19: N/A — Not disclosed | J19: N/A — Not disclosed | K19: 3851 | L19: 2410 | M19: N/A — Not disclosed | N19: N/A — Not disclosed | V19: S12 | W19: S12 | Z19: Detailed components captured for FY2022–FY2023 only.
A20: PAYABLES
A21: Trade payables / notes & accounts payable — trade | B21: ¥ million | C21: Pure trade payable balance where separately isolated. | D21: 121688 | E21: 138453 | F21: 145371 | G21: 144862 | H21: 138224 | I21: 154020 | J21: 164617 | K21: 399443 | L21: 459825 | M21: N/A — Insufficient public information to isolate reliably | N21: N/A — Insufficient public information to isolate reliably | O21: S02 | P21: S03 | Q21: S03 | R21: S05 | S21: S06 | T21: S07 | U21: S08 | V21: S12 | W21: S12 | X21: S20 | Y21: S13 | Z21: FY2024 pure trade component not isolated in retrieved notes; FY2025 uses a reposted presentation category.
A22: Accrued expenses | B22: ¥ million | C22: IFRS component of trade and other payables where retrieved. | D22: N/A — Not disclosed | E22: N/A — Not disclosed | F22: N/A — Not disclosed | G22: 60718 | H22: 63500 | I22: 67139 | J22: 87944 | K22: 213696 | L22: 245083 | M22: N/A — Insufficient public information to isolate reliably | N22: N/A — Insufficient public information to isolate reliably | R22: S05 | S22: S06 | T22: S07 | U22: S08 | V22: S12 | W22: S12 | Z22: Not supplier trade payables.
A23: Trade and other payables — audited/balance-sheet category | B23: ¥ million | C23: Published IFRS combined category. | D23: N/A — Not disclosed | E23: N/A — Not disclosed | F23: N/A — Not disclosed | G23: 359013 | H23: 359508 | I23: 419012 | J23: 462231 | K23: 857632 | L23: 975530 | M23: 1059195 | N23: N/A — Insufficient public information to isolate reliably | R23: S05 | S23: S06 | T23: S07 | U23: S08 | V23: S12 | W23: S12 | X23: S19 | Z23: Do not treat entire combined category as trade payables.
A24: Trade and other payables — FY2025 reposted presentation definition | B24: ¥ million | C24: Presentation caption explicitly marked as reposted. | D24: N/A — Not disclosed | E24: N/A — Not disclosed | F24: N/A — Not disclosed | G24: N/A — Not disclosed | H24: N/A — Not disclosed | I24: N/A — Not disclosed | J24: N/A — Not disclosed | K24: N/A — Not disclosed | L24: N/A — Not disclosed | M24: 502100 | N24: 536200 | X24: S13 | Y24: S13 | Z24: Material definition mismatch versus audited FY2024 category (¥1,059.2bn); kept separate.
A25: CONTRACT LIABILITIES / CUSTOMER ADVANCES
A26: Contract liabilities — total | B26: ¥ million | C26: IFRS total contract liabilities; early IFRS years use reported balance where no separate non-current amount was captured. | D26: N/A — Not disclosed | E26: N/A — Not disclosed | F26: 213791 | G26: 218774 | H26: 256740 | I26: 270224 | J26: 283854 | K26: 441816 | L26: 506883 | M26: 495570 | N26: N/A — Insufficient public information to isolate reliably | Q26: S05 | R26: S05 | S26: S06 | T26: S07 | U26: S08 | V26: S12 | W26: S12 | X26: S20 | Z26: FY2017 IFRS-restated; FY2025 total not isolated.
A27: Contract liabilities — current balance-sheet presentation | B27: ¥ million | C27: Current portion where separately identified. | D27: N/A — Not disclosed | E27: N/A — Not disclosed | F27: N/A — Not disclosed | G27: N/A — Not disclosed | H27: N/A — Not disclosed | I27: N/A — Not disclosed | J27: N/A — Not disclosed | K27: 417940 | L27: 480651 | M27: 471839 | N27: 500700 | V27: S10 | W27: S10 | X27: S11 | Y27: S13 | Z27: FY2025 rounded; not interchangeable with total contract liabilities.
A28: Advances received — JGAAP | B28: ¥ million | C28: JGAAP customer advances / advances received. | D28: 167738 | E28: 180827 | F28: 209746 | G28: N/A — Not disclosed | H28: N/A — Not disclosed | I28: N/A — Not disclosed | J28: N/A — Not disclosed | K28: N/A — Not disclosed | L28: N/A — Not disclosed | M28: N/A — Not disclosed | N28: N/A — Not disclosed | O28: S02 | P28: S03 | Q28: S03 | Z28: Economically related to advance billing but not equated silently with IFRS contract liabilities.
A29: Revenue recognized from opening contract-liability balance | B29: ¥ million | C29: Current-year revenue recognized from opening contract-liability balance where retrieved. | D29: N/A — Not disclosed | E29: N/A — Not disclosed | F29: N/A — Not disclosed | G29: N/A — Not disclosed | H29: N/A — Not disclosed | I29: N/A — Not disclosed | J29: N/A — Not disclosed | K29: 163503 | L29: 269947 | M29: 264608 | N29: N/A — Not disclosed | V29: S12 | W29: S12 | X29: S20 | Z29: Sparse disclosure; no interpolation.

Sheet Cash Flow
A1: NTT DATA Cash Flow — Raw Reported Data
A2: No FCF, cash-conversion or working-capital ratios are calculated. Sign and absolute-value treatments are stated explicitly.
A3: Metric metadata | D3: Reported values | O3: Source ID by fiscal year | Z3: Comparability / precision
A4: Metric | B4: Unit | C4: Definition / note | D4: FY2015 | E4: FY2016 | F4: FY2017 | G4: FY2018 | H4: FY2019 | I4: FY2020 | J4: FY2021 | K4: FY2022 | L4: FY2023 | M4: FY2024 | N4: FY2025 | O4: FY2015 | P4: FY2016 | Q4: FY2017 | R4: FY2018 | S4: FY2019 | T4: FY2020 | U4: FY2021 | V4: FY2022 | W4: FY2023 | X4: FY2024 | Y4: FY2025 | Z4: Comparability / precision
A5: STATEMENT OF CASH FLOWS
A6: Cash flow from operating activities | B6: ¥ million | C6: Reported net operating cash flow. | D6: 232751 | E6: 238552 | F6: 232282 | G6: 242000 | H6: 280000 | I6: 352500 | J6: 310400 | K6: 350600 | L6: 498789 | M6: 397148 | N6: N/A — Not disclosed | O6: S02 | P6: S03 | Q6: S03 | R6: S04 | S6: S04 | T6: S04 | U6: S04 | V6: S04 | W6: S11 | X6: S11 | Y6: S13 | Z6: FY2018–FY2022 historical official series rounded from ¥bn; FY2025 full CFS not reliably extracted.
A7: Cash flow from investing activities | B7: ¥ million | C7: Reported net investing cash flow. | D7: -188730 | E7: -428354 | F7: -208030 | G7: -186900 | H7: -257200 | I7: -173900 | J7: -196500 | K7: -322300 | L7: -624508 | M7: -669743 | N7: N/A — Not disclosed | O7: S02 | P7: S03 | Q7: S03 | R7: S04 | S7: S04 | T7: S04 | U7: S04 | V7: S04 | W7: S11 | X7: S11 | Y7: S13 | Z7: FY2018–FY2022 rounded; FY2025 gap.
A8: Cash flow from financing activities | B8: ¥ million | C8: Reported net financing cash flow. | D8: -58179 | E8: 222076 | F8: -88896 | G8: 5500 | H8: -66100 | I8: -101600 | J8: -166500 | K8: 135700 | L8: 109166 | M8: 289409 | N8: N/A — Not disclosed | O8: S02 | P8: S03 | Q8: S03 | R8: S04 | S8: S04 | T8: S04 | U8: S04 | V8: S04 | W8: S11 | X8: S11 | Y8: S13 | Z8: FY2018–FY2022 rounded; FY2025 gap.
A9: Cash and cash equivalents at year end | B9: ¥ million | C9: Reported CFS ending cash; FY2025 uses presentation statement-of-position cash because detailed CFS not extracted. | D9: 233553 | E9: 260038 | F9: 190070 | G9: 251309 | H9: 205356 | I9: 287058 | J9: 246941 | K9: 415359 | L9: 431774 | M9: 444635 | N9: 384900 | O9: S02 | P9: S03 | Q9: S03 | R9: S04 | S9: S04 | T9: S04 | U9: S04 | V9: S04 | W9: S11 | X9: S11 | Y9: S13 | Z9: FY2025 is balance-sheet cash.
A10: Capital expenditure — official KPI | B10: ¥ million | C10: Company capital-expenditure / capital-investment KPI. | D10: 134028 | E10: 158140 | F10: 198664 | G10: 179200 | H10: 193800 | I10: 169500 | J10: 176700 | K10: 381700 | L10: 657400 | M10: 675700 | N10: 635800 | O10: S03 | P10: S03 | Q10: S03 | R10: S04 | S10: S04 | T10: S04 | U10: S04 | V10: S04 | W10: S04 | X10: S13 | Y10: S13 | Z10: Some years rounded from official ¥bn KPI tables.
A11: Purchases of property, plant & equipment | B11: ¥ million | C11: Source cash outflow stored as positive absolute expenditure where captured. | D11: 47440 | E11: 67141 | F11: 99266 | G11: N/A — Not disclosed | H11: N/A — Not disclosed | I11: N/A — Not disclosed | J11: N/A — Not disclosed | K11: N/A — Not disclosed | L11: N/A — Not disclosed | M11: N/A — Not disclosed | N11: N/A — Not disclosed | O11: S02 | P11: S03 | Q11: S03 | Z11: Absolute-value storage is explicitly disclosed.
A12: Purchases of intangible assets | B12: ¥ million | C12: Source cash outflow stored as positive absolute expenditure where captured. | D12: 77922 | E12: 90939 | F12: 103647 | G12: N/A — Not disclosed | H12: N/A — Not disclosed | I12: N/A — Not disclosed | J12: N/A — Not disclosed | K12: N/A — Not disclosed | L12: N/A — Not disclosed | M12: N/A — Not disclosed | N12: N/A — Not disclosed | O12: S02 | P12: S03 | Q12: S03 | Z12: Absolute-value storage is explicitly disclosed.
A13: PP&E + intangible purchases — combined | B13: ¥ million | C13: Combined investment cash outflow where only combined value was captured. | D13: N/A — Not disclosed | E13: N/A — Not disclosed | F13: N/A — Not disclosed | G13: N/A — Not disclosed | H13: N/A — Not disclosed | I13: N/A — Not disclosed | J13: N/A — Not disclosed | K13: N/A — Not disclosed | L13: 654473 | M13: 690036 | N13: N/A — Not disclosed | W13: S11 | X13: S11 | Z13: Do not double count with separate rows.
A14: Purchase of shares of subsidiaries causing consolidation change | B14: ¥ million | C14: Acquisition cash outflow, absolute value. | D14: 28351 | E14: 6930 | F14: 4832 | G14: N/A — Not disclosed | H14: N/A — Not disclosed | I14: N/A — Not disclosed | J14: N/A — Not disclosed | K14: N/A — Not disclosed | L14: N/A — Not disclosed | M14: 77472 | N14: N/A — Not disclosed | O14: S02 | P14: S03 | Q14: S03 | X14: S11 | Z14: FY2016 Dell cash outflow also appears in equity-interest line below.
A15: Purchase of equity interests of subsidiaries causing consolidation change | B15: ¥ million | C15: Acquisition cash outflow, absolute value. | D15: N/A — Not disclosed | E15: 348431 | F15: 3543 | G15: N/A — Not disclosed | H15: N/A — Not disclosed | I15: N/A — Not disclosed | J15: N/A — Not disclosed | K15: N/A — Not disclosed | L15: N/A — Not disclosed | M15: N/A — Not disclosed | N15: N/A — Not disclosed | P15: S03 | Q15: S03 | Z15: Large FY2016 amount relates to Dell Services acquisition structure.
A16: Interest paid | B16: ¥ million | C16: Cash interest outflow, absolute value. | D16: 5544 | E16: 5377 | F16: 6164 | G16: N/A — Not disclosed | H16: N/A — Not disclosed | I16: N/A — Not disclosed | J16: N/A — Not disclosed | K16: N/A — Not disclosed | L16: N/A — Not disclosed | M16: 59642 | N16: N/A — Not disclosed | O16: S02 | P16: S03 | Q16: S03 | X16: S11 | Z16: Sparse extraction; no estimate.
A17: Income taxes paid | B17: ¥ million | C17: Cash tax outflow, absolute value. | D17: 31808 | E17: 68197 | F17: 64091 | G17: N/A — Not disclosed | H17: N/A — Not disclosed | I17: N/A — Not disclosed | J17: N/A — Not disclosed | K17: N/A — Not disclosed | L17: N/A — Not disclosed | M17: 116711 | N17: N/A — Not disclosed | O17: S02 | P17: S03 | Q17: S03 | X17: S11 | Z17: Sparse extraction.
A18: Dividends paid | B18: ¥ million | C18: Cash dividends paid, absolute value. | D18: 16834 | E18: 21037 | F18: 21739 | G18: N/A — Not disclosed | H18: N/A — Not disclosed | I18: N/A — Not disclosed | J18: N/A — Not disclosed | K18: N/A — Not disclosed | L18: N/A — Not disclosed | M18: 33658 | N18: N/A — Not disclosed | O18: S02 | P18: S03 | Q18: S03 | X18: S11 | Z18: Sparse extraction.
A19: Proceeds from long-term debt / bonds | B19: ¥ million | C19: Debt issuance cash inflow where captured. | D19: N/A — Not disclosed | E19: 115512 | F19: 187617 | G19: N/A — Not disclosed | H19: N/A — Not disclosed | I19: N/A — Not disclosed | J19: N/A — Not disclosed | K19: N/A — Not disclosed | L19: N/A — Not disclosed | M19: 738544 | N19: N/A — Not disclosed | P19: S03 | Q19: S03 | X19: S11 | Z19: FY2024 captured combined issuance/borrowing line.
A20: Repayments / redemption of long-term debt and bonds | B20: ¥ million | C20: Debt repayment cash outflow, absolute value. | D20: N/A — Not disclosed | E20: 29331 | F20: 103785 | G20: N/A — Not disclosed | H20: N/A — Not disclosed | I20: N/A — Not disclosed | J20: N/A — Not disclosed | K20: N/A — Not disclosed | L20: N/A — Not disclosed | M20: 266694 | N20: N/A — Not disclosed | P20: S03 | Q20: S03 | X20: S11 | Z20: FY2017 combines reported ¥50,000mm bond redemption and ¥53,785mm long-term-loan repayment; mechanical aggregation is labelled.
A21: Lease repayments | B21: ¥ million | C21: Lease cash outflow, absolute value. | D21: N/A — Not disclosed | E21: 3129 | F21: 2684 | G21: N/A — Not disclosed | H21: N/A — Not disclosed | I21: N/A — Not disclosed | J21: N/A — Not disclosed | K21: N/A — Not disclosed | L21: N/A — Not disclosed | M21: 80020 | N21: N/A — Not disclosed | P21: S03 | Q21: S03 | X21: S11 | Z21: Presentation changes after IFRS 16.
A22: REPORTED WORKING-CAPITAL CASH-FLOW MOVEMENTS
A23: Change in trade / trade & other receivables | B23: ¥ million | C23: Reported CFS working-capital movement; signs retained as cash-flow effect. | D23: -43052 | E23: -9032 | F23: -40133 | G23: N/A — Not disclosed | H23: N/A — Not disclosed | I23: -22477 | J23: -42933 | K23: N/A — Not disclosed | L23: -16427 | M23: -143722 | N23: N/A — Not disclosed | O23: S02 | P23: S03 | Q23: S03 | T23: S07 | U23: S08 | W23: S11 | X23: S11 | Z23: Caption changes from JGAAP trade AR to IFRS trade & other receivables.
A24: Change in contract assets | B24: ¥ million | C24: Reported CFS movement; signs retained. | D24: N/A — Not disclosed | E24: N/A — Not disclosed | F24: N/A — Not disclosed | G24: N/A — Not disclosed | H24: N/A — Not disclosed | I24: -24602 | J24: -1593 | K24: N/A — Not disclosed | L24: -21054 | M24: -45488 | N24: N/A — Not disclosed | T24: S07 | U24: S08 | W24: S11 | X24: S11 | Z24: Sparse extraction.
A25: Change in inventories | B25: ¥ million | C25: Reported CFS movement; signs retained. | D25: 5373 | E25: -4497 | F25: -8302 | G25: N/A — Not disclosed | H25: N/A — Not disclosed | I25: -855 | J25: -10780 | K25: N/A — Not disclosed | L25: 30105 | M25: -3905 | N25: N/A — Not disclosed | O25: S02 | P25: S03 | Q25: S03 | T25: S07 | U25: S08 | W25: S11 | X25: S11 | Z25: Sign is cash-flow effect, not balance delta.
A26: Change in trade / trade & other payables | B26: ¥ million | C26: Reported CFS movement; signs retained. | D26: 9574 | E26: 16609 | F26: 9904 | G26: N/A — Not disclosed | H26: N/A — Not disclosed | I26: 50358 | J26: 27833 | K26: N/A — Not disclosed | L26: -22651 | M26: 104086 | N26: N/A — Not disclosed | O26: S02 | P26: S03 | Q26: S03 | T26: S07 | U26: S08 | W26: S11 | X26: S11 | Z26: Caption changes across frameworks.
A27: Change in contract liabilities / advances received | B27: ¥ million | C27: JGAAP advances received, IFRS contract liabilities; signs retained. | D27: 27954 | E27: 14908 | F27: 27637 | G27: N/A — Not disclosed | H27: N/A — Not disclosed | I27: 11018 | J27: 920 | K27: N/A — Not disclosed | L27: 29985 | M27: -7930 | N27: N/A — Not disclosed | O27: S02 | P27: S03 | Q27: S03 | T27: S07 | U27: S08 | W27: S11 | X27: S11 | Z27: JGAAP advances received is not necessarily identical to IFRS contract liabilities.

Sheet Segments
A1: NTT DATA Segments / Geography / Service Mix
A2: Long-form table preserves company-reported labels rather than forcing inconsistent historical categories into one taxonomy.
A4: Fiscal year | B4: Reporting basis | C4: Breakdown type | D4: Reported label | E4: Revenue (¥ million) | F4: Operating profit (¥ million) | G4: Source ID | H4: Source note | I4: Comparability warning
A5: FY2015 | B5: JGAAP | C5: Geography / historic KPI | D5: Overseas net sales | E5: 504400 | F5: N/A — Not disclosed | G5: S04 | H5: Official historical KPI series | I5: Definition evolves with overseas organization; do not force-map to current Overseas Segment.
A6: FY2016 | B6: JGAAP | C6: Geography / historic KPI | D6: Overseas net sales | E6: 586300 | F6: N/A — Not disclosed | G6: S04 | H6: Official historical KPI series | I6: Definition evolves with overseas organization; do not force-map to current Overseas Segment.
A7: FY2017 | B7: JGAAP | C7: Geography / historic KPI | D7: Overseas net sales | E7: 911100 | F7: N/A — Not disclosed | G7: S04 | H7: Official historical KPI series | I7: Definition evolves with overseas organization; do not force-map to current Overseas Segment.
A8: FY2018 | B8: IFRS | C8: Geography / historic KPI | D8: Overseas net sales | E8: 881100 | F8: N/A — Not disclosed | G8: S04 | H8: Official historical KPI series | I8: Definition evolves with overseas organization; do not force-map to current Overseas Segment.
A9: FY2019 | B9: IFRS | C9: Geography / historic KPI | D9: Overseas net sales | E9: 906700 | F9: N/A — Not disclosed | G9: S04 | H9: Official historical KPI series | I9: Definition evolves with overseas organization; do not force-map to current Overseas Segment.
A10: FY2020 | B10: IFRS | C10: Geography / historic KPI | D10: Overseas net sales | E10: 907200 | F10: N/A — Not disclosed | G10: S04 | H10: Official historical KPI series | I10: Definition evolves with overseas organization; do not force-map to current Overseas Segment.
A11: FY2021 | B11: IFRS | C11: Geography / historic KPI | D11: Overseas net sales | E11: 1050500 | F11: N/A — Not disclosed | G11: S04 | H11: Official historical KPI series | I11: Definition evolves with overseas organization; do not force-map to current Overseas Segment.
A12: FY2022 | B12: IFRS | C12: Geography / historic KPI | D12: Overseas net sales | E12: 1866100 | F12: N/A — Not disclosed | G12: S04 | H12: Official historical KPI series | I12: Definition evolves with overseas organization; do not force-map to current Overseas Segment.
A13: FY2023 | B13: IFRS | C13: Geography / historic KPI | D13: Overseas net sales | E13: 2636300 | F13: N/A — Not disclosed | G13: S04 | H13: Official historical KPI series | I13: Definition evolves with overseas organization; do not force-map to current Overseas Segment.
A14: FY2024 | B14: IFRS | C14: Current segment | D14: Japan Segment | E14: 1893893 | F14: N/A — Not disclosed | G14: S13 | H14: FY2025 presentation comparative | I14: Three-company structure; some segment figures rounded in presentation.
A15: FY2024 | B15: IFRS | C15: Current segment | D15: Overseas Segment | E15: 2731390 | F15: N/A — Not disclosed | G15: S13 | H15: FY2025 presentation comparative | I15: Three-company structure; some segment figures rounded in presentation.
A16: FY2024 | B16: IFRS | C16: Current segment | D16: Public & Social Infrastructure | E16: 669900 | F16: N/A — Not disclosed | G16: S13 | H16: FY2025 presentation comparative | I16: Three-company structure; some segment figures rounded in presentation.
... A35: FY2025 | B35: IFRS | C35: Service category | D35: Communication terminal equipment sales / etc. / others | E35: 1007800 | F35: N/A — Not disclosed | G35: S13 | H35: FY2025 presentation | I35: Rounded to ¥0.1bn.

Sheet Orders & Backlog
A1: NTT DATA Orders & Backlog
A2: Raw order intake/new orders and year-end backlog. No order-growth or book-to-bill calculation is included.
A4: Fiscal year | B4: Accounting basis | C4: New orders / order intake (¥ million) | D4: Year-end order backlog (¥ million) | E4: Source ID | F4: Definition / scope note | G4: Selected contract / order commentary | H4: Comparability warning
A5: FY2015 | B5: JGAAP | C5: 1662662 | D5: 1544500 | E5: S03
A6: FY2016 | B6: JGAAP | C6: 1781565 | D6: 2411300 | E6: S03 | G6: Former Dell Services acquisition materially expanded international business scale; management also highlighted the myki operations contract. | H6: Acquisition/consolidation effects materially affect backlog and sales base.
A7: FY2017 | B7: JGAAP | C7: 2021195 | D7: 2371500 | E7: S03
A8: FY2018 | B8: IFRS | C8: 2076100 | D8: 2457100 | E8: S04
A9: FY2019 | B9: IFRS | C9: 2275200 | D9: 2636300 | E9: S04
A10: FY2020 | B10: IFRS | C10: 2223300 | D10: 2735100 | E10: S04
A11: FY2021 | B11: IFRS | C11: 2400800 | D11: 2860600 | E11: S04
A12: FY2022 | B12: IFRS | C12: 2725600 | D12: 4653900 | E12: S09 | F12: Management states FY2022 new orders exclude NTT Ltd.; financial results/balance sheet include NTT Ltd. from Q3. | H12: Structural scope break.
A13: FY2023 | B13: IFRS | C13: 4790900 | D13: 5859600 | E13: S10 | F13: NTT Ltd. included in order intake under expanded group scope. | H13: First full-year order series with expanded overseas scope.
A14: FY2024 | B14: IFRS | C14: 4961600 | D14: 6401200 | E14: S13
A15: FY2025 | B15: IFRS | C15: 6010500 | D15: 8240300 | E15: S13 | F15: Presentation values in ¥bn to one decimal. | H15: Rounded source precision.

Sheet Debt & Financing
A1: NTT DATA Debt & Financing
A2: Raw financing balances, finance costs and selected rating history. No estimated cost of debt is included.
A4: Fiscal year | B4: Basis | C4: Metric | D4: Reported value | E4: Unit | F4: Source ID | G4: Source context | H4: Maturity / rate note | I4: Rating / refinancing note | J4: Comparability warning
A5: FY2015 | B5: JGAAP | C5: Short-term loans payable | D5: 51627 | E5: ¥ million | F5: S02 | G5: Annual report | H5: N/A — Not disclosed | I5: N/A — Not disclosed
A6: FY2015 | B6: JGAAP | C6: Current portion LT loans | D6: 29245 | E6: ¥ million | F6: S02 | G6: Annual report | H6: N/A — Not disclosed | I6: N/A — Not disclosed
A7: FY2015 | B7: JGAAP | C7: Bonds payable — non-current | D7: 210062 | E7: ¥ million | F7: S02 | G7: Annual report | H7: N/A — Not disclosed | I7: N/A — Not disclosed
A8: FY2015 | B8: JGAAP | C8: Long-term loans payable | D8: 109451 | E8: ¥ million | F8: S02 | G8: Annual report | H8: N/A — Not disclosed | I8: N/A — Not disclosed
A9: FY2015 | B9: JGAAP | C9: Interest-bearing debt — company KPI | D9: 400387 | E9: ¥ million | F9: S02 | G9: Annual report | H9: N/A — Not disclosed | I9: N/A — Not disclosed
A10: FY2015 | B10: JGAAP | C10: Interest expense | D10: 5492 | E10: ¥ million | F10: S02 | G10: Annual report | H10: N/A — Not disclosed | I10: N/A — Not disclosed
A11: FY2016 | B11: JGAAP | C11: Short-term loans payable | D11: 213160 | E11: ¥ million | F11: S03 | G11: Annual report | H11: N/A — Not disclosed | I11: N/A — Not disclosed
A12: FY2016 | B12: JGAAP | C12: Current portion LT loans | D12: 53461 | E12: ¥ million | F12: S03 | G12: Annual report | H12: N/A — Not disclosed | I12: N/A — Not disclosed
A13: FY2016 | B13: JGAAP | C13: Current portion bonds | D13: 49996 | E13: ¥ million | F13: S03 | G13: Annual report | H13: N/A — Not disclosed | I13: N/A — Not disclosed
A14: FY2016 | B14: JGAAP | C14: Bonds payable — non-current | D14: 160075 | E14: ¥ million | F14: S03 | G14: Annual report | H14: N/A — Not disclosed | I14: N/A — Not disclosed
A15: FY2016 | B15: JGAAP | C15: Long-term loans payable | D15: 168618 | E15: ¥ million | F15: S03 | G15: Annual report | H15: N/A — Not disclosed | I15: N/A — Not disclosed
A16: FY2016 | B16: JGAAP | C16: Interest-bearing debt — company KPI | D16: 650814 | E16: ¥ million | F16: S03 | G16: Annual report | H16: N/A — Not disclosed | I16: N/A — Not disclosed
... A26: FY2018 | B26: IFRS | C26: Bonds and borrowings — non-current | D26: 446437 | E26: ¥ million | F26: S05 | G26: Official statement / presentation | H26: N/A — Not disclosed | I26: N/A — Not disclosed
A27: FY2018 | B27: IFRS | C27: Lease liabilities — current | D27: N/A — Not disclosed | E27: ¥ million | F27: S05 | G27: Official statement / presentation | H27: N/A — Not disclosed | I27: N/A — Not disclosed
A28: FY2018 | B28: IFRS | C28: Lease liabilities — non-current | D28: N/A — Not disclosed | E28: ¥ million | F28: S05 | G28: Official statement / presentation | H28: N/A — Not disclosed | I28: N/A — Not disclosed
A29: FY2018 | B29: IFRS | C29: Finance costs | D29: 7825 | E29: ¥ million | F29: S05 | G29: Official statement / presentation | H29: N/A — Not disclosed | I29: N/A — Not disclosed
A30: FY2019 | B30: IFRS | C30: Bonds and borrowings — current | D30: 157094 | E30: ¥ million | F30: S06 | G30: Official statement / presentation | H30: N/A — Not disclosed | I30: N/A — Not disclosed
A31: FY2019 | B31: IFRS | C31: Bonds and borrowings — non-current | D31: 440861 | E31: ¥ million | F31: S06 | G31: Official statement / presentation | H31: N/A — Not disclosed | I31: N/A — Not disclosed
A32: FY2019 | B32: IFRS | C32: Lease liabilities — current | D32: 39143 | E32: ¥ million | F32: S06 | G32: Official statement / presentation | H32: N/A — Not disclosed | I32: N/A — Not disclosed
A33: FY2019 | B33: IFRS | C33: Lease liabilities — non-current | D33: 122219 | E33: ¥ million | F33: S06 | G33: Official statement / presentation | H33: N/A — Not disclosed | I33: N/A — Not disclosed
A34: FY2019 | B34: IFRS | C34: Finance costs | D34: 17117 | E34: ¥ million | F34: S06 | G34: Official statement / presentation | H34: N/A — Not disclosed | I34: N/A — Not disclosed
A35: FY2020 | B35: IFRS | C35: Bonds and borrowings — current | D35: 105748 | E35: ¥ million | F35: S07 | G35: Official statement / presentation | H35: N/A — Not disclosed | I35: N/A — Not disclosed
A36: FY2020 | B36: IFRS | C36: Bonds and borrowings — non-current | D36: 473154 | E36: ¥ million | F36: S07 | G36: Official statement / presentation | H36: N/A — Not disclosed | I36: N/A — Not disclosed
A37: FY2020 | B37: IFRS | C37: Lease liabilities — current | D37: 41439 | E37: ¥ million | F37: S07 | G37: Official statement / presentation | H37: N/A — Not disclosed | I37: N/A — Not disclosed
A38: FY2020 | B38: IFRS | C38: Lease liabilities — non-current | D38: 117866 | E38: ¥ million | F38: S07 | G38: Official statement / presentation | H38: N/A — Not disclosed | I38: N/A — Not disclosed
A39: FY2020 | B39: IFRS | C39: Finance costs | D39: 9083 | E39: ¥ million | F39: S07 | G39: Official statement / presentation | H39: N/A — Not disclosed | I39: N/A — Not disclosed
A40: FY2021 | B40: IFRS | C40: Bonds and borrowings — current | D40: 102829 | E40: ¥ million | F40: S08 | G40: Official statement / presentation | H40: N/A — Not disclosed | I40: N/A — Not disclosed
... A59: FY2024 | B59: IFRS | C59: Finance costs | D59: 105838 | E59: ¥ million | F59: S11 | G59: Official statement / presentation | H59: N/A — Not disclosed | I59: N/A — Not disclosed
A60: FY2025 | B60: IFRS | C60: Bonds and borrowings — current | D60: 732300 | E60: ¥ million | F60: S13 | G60: Official statement / presentation | H60: N/A — Not disclosed | I60: N/A — Not disclosed | J60: FY2025 rounded.
A61: FY2025 | B61: IFRS | C61: Bonds and borrowings — non-current | D61: 2102800 | E61: ¥ million | F61: S13 | G61: Official statement / presentation | H61: N/A — Not disclosed | I61: N/A — Not disclosed | J61: FY2025 rounded.
A62: FY2025 | B62: IFRS | C62: Lease liabilities — current | D62: N/A — Not disclosed | E62: ¥ million | F62: S13 | G62: Official statement / presentation | H62: N/A — Not disclosed | I62: N/A — Not disclosed | J62: FY2025 rounded.
A63: FY2025 | B63: IFRS | C63: Lease liabilities — non-current | D63: 174000 | E63: ¥ million | F63: S13 | G63: Official statement / presentation | H63: N/A — Not disclosed | I63: N/A — Not disclosed | J63: FY2025 rounded.
A64: FY2025 | B64: IFRS | C64: Finance costs | D64: N/A — Not disclosed | E64: ¥ million | F64: S13 | G64: Official statement / presentation | H64: N/A — Not disclosed | I64: N/A — Not disclosed | J64: FY2025 rounded.
A65: FY2018 | B65: IFRS | C65: Interest-bearing debt — official KPI | D65: 605000 | E65: ¥ million | F65: S04 | G65: Company historical KPI / presentation | H65: N/A — Not disclosed | I65: N/A — Not disclosed | J65: Directly reported KPI; not reconstructed.
A66: FY2019 | B66: IFRS | C66: Interest-bearing debt — official KPI | D66: 598000 | E66: ¥ million | F66: S04 | G66: Company historical KPI / presentation | H66: N/A — Not disclosed | I66: N/A — Not disclosed | J66: Directly reported KPI; not reconstructed.
A67: FY2020 | B67: IFRS | C67: Interest-bearing debt — official KPI | D67: 578900 | E67: ¥ million | F67: S04 | G67: Company historical KPI / presentation | H67: N/A — Not disclosed | I67: N/A — Not disclosed | J67: Directly reported KPI; not reconstructed.
A68: FY2021 | B68: IFRS | C68: Interest-bearing debt — official KPI | D68: 496500 | E68: ¥ million | F68: S04 | G68: Company historical KPI / presentation | H68: N/A — Not disclosed | I68: N/A — Not disclosed | J68: Directly reported KPI; not reconstructed.
A69: FY2024 | B69: IFRS | C69: Interest-bearing debt — official KPI | D69: 2599100 | E69: ¥ million | F69: S13 | G69: Company historical KPI / presentation | H69: N/A — Not disclosed | I69: N/A — Not disclosed | J69: Directly reported KPI; not reconstructed.
A70: FY2025 | B70: IFRS | C70: Interest-bearing debt — official KPI | D70: 2835100 | E70: ¥ million | F70: S13 | G70: Company historical KPI / presentation | H70: N/A — Not disclosed | I70: N/A — Not disclosed | J70: Directly reported KPI; not reconstructed.
A71: FY2017 | B71: JGAAP | C71: Credit rating — JCR | D71: AA+ | E71: rating | F71: S03 | G71: Annual Report 2018 | H71: N/A — Not disclosed | I71: JCR AA+ | J71: Snapshot.
A72: FY2017 | B72: JGAAP | C72: Credit rating — R&I | D72: AA | E72: rating | F72: S03 | G72: Annual Report 2018 | H72: N/A — Not disclosed | I72: R&I AA | J72: Snapshot.
A73: FY2020 | B73: IFRS | C73: Credit rating — JCR | D73: AA+ | E73: rating | F73: S07 | G73: Integrated Report 2020 | H73: N/A — Not disclosed | I73: JCR AA+ | J73: Snapshot.
A74: FY2020 | B74: IFRS | C74: Credit rating — R&I | D74: AA | E74: rating | F74: S07 | G74: Integrated Report 2020 | H74: N/A — Not disclosed | I74: R&I AA | J74: Snapshot.
A75: FY2021 | B75: IFRS | C75: Credit rating — R&I | D75: AA+ | E75: rating | F75: S08 | G75: FY2021 management material | H75: N/A — Not disclosed | I75: Upgraded from AA to AA+ on Dec. 1, 2021 | J75: Rating-change event.
A76: FY2021 | B76: IFRS | C76: Credit rating — JCR | D76: AA+ | E76: rating | F76: S04 | G76: Integrated Report 2022 reference | H76: N/A — Not disclosed | I76: JCR AA+ | J76: Snapshot.

Sheet Acq & Structural Changes
A1: NTT DATA Acquisitions & Structural Changes
A2: Events that can distort revenue, working capital, debt, cash flow, segment mix or accounting comparability.
A4: Fiscal year | B4: Date | C4: Event | D4: Company / business | E4: Event type | F4: Purchase price / consideration | G4: Key disclosed financial impact | H4: Metrics affected | I4: Comparability impact | J4: Source ID | K4: Source note
A5: FY2016 | B5: 2016-11-02 | C5: Acquisition of former Dell Services | D5: Dell Services | E5: Acquisition / carve-out | F5: ¥345,375 million | G5: Former Dell Services generated roughly ¥300bn annual sales; acquisition financed partly with ¥210bn short-term borrowing and created a major acquisition cash outflow. | H5: Revenue; receivables; debt; cash flow; overseas mix; backlog | I5: Major structural break from FY2016 onward; acquired scale is not organic working-capital movement. | J5: S16 | K5: Official business-combination disclosure.
A6: FY2017 | B6: 2017-04-01 | C6: North America integration of former Dell Services | D6: NTT DATA Services / NTT DATA, Inc. | E6: Post-merger integration | F6: N/A — Not disclosed | G6: North American operating structure integrated; acquisition-related operating/IT transition costs continued. | H6: Revenue; operating costs; segment mix | I6: Historical Global/overseas trends include post-acquisition integration effects. | J6: S15 | K6: Official acquisition / annual-report commentary.
A7: FY2017 | B7: 2017-04-01 transition date | C7: Transition from Japanese GAAP to IFRS reporting series | D7: NTT DATA Group | E7: Accounting-standard change | F7: N/A — Not disclosed | G7: Official data archive maintains JGAAP-through-FY2017 and IFRS-from-FY2018 series; IFRS-restated FY2017 bridge data exist. | H7: All statement captions; contract balances; classifications | I7: Main workbook uses JGAAP FY2015–FY2017 and IFRS FY2018+; bridge values are explicitly labelled. | J7: S01 | K7: Official Data Tables split.
A8: FY2019 | B8: FY2019 reporting year | C8: IFRS 16 lease presentation becomes visible | D8: NTT DATA Group | E8: Accounting-policy / presentation change | F8: N/A — Not disclosed | G8: Right-of-use assets and current/non-current lease liabilities become separately visible in retrieved statements. | H8: Assets; liabilities; lease payments; capital intensity | I8: Lease-sensitive comparisons around FY2019 require care. | J8: S06 | K8: FY2019 financial statements.
A9: FY2022 | B9: 2022-10-01 | C9: Establishment of NTT DATA, Inc. / business combination with NTT Ltd. | D9: NTT Ltd. / NTT DATA, Inc. | E9: Common-control business combination / reorganization | F9: N/A — Not disclosed | G9: Disclosed acquired/consolidated balances included trade & other receivables ¥975,363mm, PP&E ¥971,376mm, goodwill ¥560,493mm, intangibles ¥119,879mm, trade/other payables ¥621,976mm and bonds/borrowings ¥1,041,612mm. | H9: Revenue; AR; contract assets; AP; debt; assets; segment mix; cash flow | I9: Largest structural break in the IFRS series. FY2022 balance sheet includes NTT Ltd.; FY2022 new orders exclude it. | J9: S12 | K9: Audited notes describing FY2022 common-control combination.
A10: FY2023 | B10: 2023-07-01 | C10: Transition to three-company holding-company structure | D10: NTT DATA Group Corporation; NTT DATA Japan; NTT DATA, Inc. | E10: Corporate reorganization | F10: N/A — Not disclosed | G10: Domestic and overseas operating companies placed under holding company; governance and reporting structure changed. | H10: Segments; reporting labels; governance | I10: Current Japan/Overseas segment labels are not directly comparable with older historical segments. | J10: S17 | K10: Integrated Report 2023.
A11: FY2024 | B11: 2024–2025 | C11: Data-center assets held for sale / disposal process | D11: Overseas data-center businesses | E11: Asset disposal / held-for-sale classification | F11: N/A — Not disclosed | G11: Assets held for sale reached ¥93,060mm at Mar. 31, 2025; disposal process continued into FY2025. | H11: PP&E; investing cash flow; operating profit; segment mix | I11: One-off asset-sale accounting can distort asset and profit trends. | J11: S11 | K11: FY2024 final results.
A12: FY2025 | B12: 2025-06/07 updates; FY2025 result impact | C12: Data-center fixed-asset transfer/disposal | D12: Consolidated data-center subsidiaries | E12: Asset disposal | F12: N/A — Not disclosed | G12: Company presentation identifies a material data-center transfer transaction and gain affecting reported operating profit / EBITDA. | H12: Operating profit; EBITDA; PP&E; investing cash flow | I12: FY2025 operating-profit/EBITDA improvement contains a material one-off transaction effect. | J12: S13 | K12: FY2025 presentation / timely-disclosure context.
A13: FY2025 | B13: 2025-09-26 | C13: Delisting from Tokyo Stock Exchange Prime Market | D13: NTT DATA Group Corporation | E13: Ownership / listing change | F13: N/A — Not disclosed | G13: Shares delisted after shareholder-approved share consolidation as NTT moved to full ownership. | H13: Ownership; disclosure regime; future IR availability | I13: FY2025 includes a major ownership/governance change; future public-disclosure format may differ. | J13: S18 | K13: Official Notice of Delisting.

Sheet Qualitative Evidence
A1: NTT DATA Qualitative Working-Capital Evidence
A2: Management explanations and accounting-policy evidence. Analyst interpretation is intentionally minimized in Phase 1.
A4: Fiscal year / date | B4: Topic | C4: Management statement summary | D4: Related metric | E4: Explanation / accounting meaning | F4: Source document | G4: Page / section | H4: Source ID | I4: URL | J4: Classification
A5: FY2024 statutory note | B5: Contract assets | C5: Contract assets record consideration for system-development services in progress and move to trade receivables when the right to payment becomes unconditional. | D5: Contract assets; trade AR | E5: Key bridge between unbilled project work and invoiced receivables. | F5: FY2024 statutory financial statements | G5: Contract balance | H5: S20 | I5: https://www.nttdata.com/global/en/-/media/nttdataglobal/1_files/investors/stock-information/2025/web37_e.pdf?rev=2a93a0492d5b471ebd6d02c370fb6786 | J5: Management / accounting policy
A6: FY2024 statutory note | B6: Contract liabilities | C6: Contract liabilities record client consideration received in advance and are derecognized as corresponding goods/services transfer. | D6: Contract liabilities; customer advances | E6: Advance billing can fund the operating cycle and should remain separate from ordinary payables. | F6: FY2024 statutory financial statements | G6: Contract balance | H6: S20 | I6: https://www.nttdata.com/global/en/-/media/nttdataglobal/1_files/investors/stock-information/2025/web37_e.pdf?rev=2a93a0492d5b471ebd6d02c370fb6786 | J6: Management / accounting policy
A7: FY2023 notes | B7: Credit risk / collections | C7: Management monitors individual customer collection status, due dates and credit balances in receivable-credit management. | D7: Receivables / ECL | E7: Relevant to later collection-quality analysis; does not quantify standard payment terms. | F7: Integrated Report 2024 — notes | G7: Financial instruments / credit risk | H7: S12 | I7: https://www.nttdata.com/global/en/-/media/nttdataglobal/1_files/investors/integrated-report/fy2024_ar.pdf | J7: Management explanation
A8: FY2016 | B8: Dell Services acquisition | C8: Management characterized the acquisition as a major expansion of North American scale; separate disclosures show acquisition/integration costs and borrowing used to fund it. | D8: Revenue; debt; cash flow; backlog | E8: Acquired scale changes denominators and balance-sheet levels for later trend analysis. | F8: Annual Report / transaction disclosure | G8: Dell Services acquisition | H8: S16 | I8: https://www.nttdata.com/global/en/-/media/nttdataglobal/files/investors/inv004_financials/financial-results/2016/fy2016_fs_2q.pdf?rev=3e91ad1a036f43fb953c6c3c8c3ec724 | J8: Management explanation
A9: FY2016 | B9: Accounting-period alignment | C9: Management stated that unification of some EMEA accounting periods added about ¥21bn to sales and ¥16bn to new orders in the year. | D9: Revenue; orders | E9: Calendar/consolidation effect, not purely operating growth. | F9: Official IR Q&A | G9: EMEA accounting period | H9: S03 | I9: https://www.nttdata.com/global/en/investors/principal-qa-2017-3q | J9: Management explanation
A10: FY2022 | B10: NTT Ltd. combination | C10: The overseas business combination with NTT Ltd. greatly expanded group scale and added data-center, managed-services, network and other businesses. | D10: Revenue; AR; AP; debt; PP&E; goodwill | E10: Most important structural explanation for FY2022 balance-sheet step-up. | F10: Integrated Report 2023 / audited notes | G10: Reorganization / business combination | H10: S17 | I10: https://www.nttdata.com/global/en/-/media/nttdataglobal/1_files/investors/integrated-report/fy2023_ar_b.pdf?rev=aed9c74c1a4d43a18ad6c81cb18a8f5e | J10: Management explanation
A11: FY2022–FY2023 | B11: Orders | C11: Management materials state FY2022 new orders exclude NTT Ltd., while NTT Ltd. is included from FY2023. | D11: Orders / backlog | E11: Order growth across the boundary is not like-for-like. | F11: FY2025 Company Presentation | G11: Historical order trend note | H11: S13 | I11: https://www.nttdata.com/global/en/-/media/nttdataglobal/1_files/investors/ir_events/2025/fy2025_pre_4q.pdf | J11: Management explanation
A12: FY2023 | B12: Loss-making project | C12: Management discussed a loss-making Public & Social Infrastructure project; after launch, the system issue was resolved and operations were moving into a smaller maintenance phase. | D12: Operating profit; project WIP / contract assets | E12: Large systems projects can create project-timing and acceptance effects relevant to contract assets. | F12: Integrated Report 2024 | G12: Business performance | H12: S12 | I12: https://www.nttdata.com/global/en/-/media/nttdataglobal/1_files/investors/integrated-report/fy2024_ar.pdf | J12: Management explanation
A13: FY2023 | B13: Capital investment / data centers | C13: Management reported substantial overseas capital investment, with a large portion related to data centers. | D13: PP&E; investing cash flow | E13: Capital-intensive data-center expansion is economically separate from working capital. | F13: Integrated Report 2024 | G13: Capital expenditures | H13: S12 | I13: https://www.nttdata.com/global/en/-/media/nttdataglobal/1_files/investors/integrated-report/fy2024_ar.pdf | J13: Management explanation
A14: FY2025 | B14: Data-center transfer / disposal | C14: FY2025 presentation indicates a material data-center transfer transaction gain contributing to operating profit and EBITDA. | D14: Operating profit; EBITDA; PP&E | E14: One-off transaction gain should not be mistaken for better operating-cycle cash conversion. | F14: FY2025 Company Presentation | G14: Consolidated results | H14: S13 | I14: https://www.nttdata.com/global/en/-/media/nttdataglobal/1_files/investors/ir_events/2025/fy2025_pre_4q.pdf | J14: Management explanation
A15: FY2025 | B15: Balance-sheet reposting | C15: FY2025 presentation explicitly labels some balance-sheet breakdown items as reposted. | D15: Receivables; payables | E15: Reposted FY2024 comparatives do not reconcile to audited FY2024 detailed captions; both definitions are preserved separately. | F15: FY2025 Company Presentation | G15: Statement of financial position | H15: S13 | I15: https://www.nttdata.com/global/en/-/media/nttdataglobal/1_files/investors/ir_events/2025/fy2025_pre_4q.pdf | J15: Accounting / presentation warning

Sheet Sources
A1: Source Register
A2: Primary-source register. Source IDs are used throughout the workbook for point-level traceability.
A4: Source ID | B4: Document name | C4: Document type | D4: Fiscal year(s) | E4: Publication date | F4: URL | G4: Audit / status | H4: Relevant pages / sections | I4: Comments
A5: S01 | B5: NTT DATA Data Tables | C5: Official IR data archive | D5: FY2015–FY2026 | E5: 2026-08-06 | F5: https://www.nttdata.com/global/en/investors/performance/fb | G5: Official IR | H5: Data Tables page | I5: JGAAP through FY2017; IFRS from FY2018; updated after results.
A6: S02 | B6: Annual Report 2017 | C6: Annual report / audited financial statements | D6: FY2015–FY2016 | E6: 2017 | F6: https://www.nttdata.com/global/en/-/media/nttdataglobal/files/investors/inv004_financials/annual-report/fy2017_ar_b.pdf?rev=b1cb8171510c438d93f85170ef462b95 | G6: Audited | H6: Financial statements / notes | I6: Primary source for FY2015 and FY2016 JGAAP.
A7: S03 | B7: Annual Report 2018 | C7: Annual report / audited financial statements | D7: FY2016–FY2017 | E7: 2018 | F7: https://www.nttdata.com/global/en/-/media/nttdataglobal/files/investors/inv004_financials/annual-report/fy2018_ar_b.pdf?rev=6133c7d3db8942d8a5b0c640965b5fed | G7: Audited | H7: Financial Information; historical highlights | I7: Primary source for FY2016–FY2017 JGAAP and historical KPI values.
A8: S04 | B8: Integrated Report 2022 | C8: Integrated report / historical financial data | D8: FY2017–FY2022 | E8: 2022 | F8: https://www.nttdata.com/global/en/-/media/nttdataglobal/1_files/investors/integrated-report/fy2022_ar_b.pdf | G8: Audited financial data + management report | H8: Historical financial / non-financial data | I8: Orders, backlog, capex, EBITDA, overseas sales and rating history.
A9: S05 | B9: Integrated Report / Annual Report 2019 | C9: Audited IFRS report | D9: FY2018 | E9: 2019 | F9: https://www.nttdata.com/global/en/-/media/nttdataglobal/1_files/investors/integrated-report/fy2019_ar_b.pdf?rev=cf6cd677f4d3420094b591b4c92b6af4 | G9: Audited | H9: Consolidated statements / notes | I9: IFRS statement-of-position and working-capital breakdown.
A10: S06 | B10: FY2019 Financial Results | C10: Kessan Tanshin / final results | D10: FY2019 | E10: 2020 | F10: https://www.nttdata.com/global/en/-/media/nttdataglobal/1_files/investors/financial-results/2019/fy2019_fs_4q_01.pdf | G10: Official; Kessan Tanshin | H10: Consolidated statements | I10: FY2019 income and balance data.
A11: S07 | B11: Integrated Report 2020 | C11: Audited IFRS report | D11: FY2020 | E11: 2021 | F11: https://www.nttdata.com/global/en/-/media/nttdataglobal/1_files/investors/integrated-report/fy2020_ar_b.pdf?rev=3eb817c598a641959792e94610b81324 | G11: Audited | H11: Financial statements / management resources | I11: FY2020 IFRS and rating information.
A12: S08 | B12: Integrated Report 2021 | C12: Audited IFRS report | D12: FY2021 | E12: 2022 | F12: https://www.nttdata.com/global/en/-/media/nttdataglobal/1_files/investors/integrated-report/fy2021_ar_b.pdf?rev=7b868a5c0f1a4c50b7eb6bce7f4c80e1 | G12: Audited | H12: Financial statements / management resources | I12: FY2021 IFRS and rating context.
A13: S09 | B13: FY2022 Financial Results | C13: Kessan Tanshin / final results | D13: FY2022 | E13: 2023 | F13: https://www.nttdata.com/global/en/-/media/nttdataglobal/1_files/investors/financial-results/2022/fy2022_fs_4q.pdf | G13: Official; Kessan Tanshin | H13: Consolidated statements | I13: FY2022 statement figures.
A14: S10 | B14: FY2023 Financial Results | C14: Kessan Tanshin / final results | D14: FY2023 | E14: 2024 | F14: https://www.nttdata.com/global/en/-/media/nttdataglobal/1_files/investors/financial-results/2023/fy2023_fs_4q.pdf?rev=362f0f5a70cf43628c53baadd69caee6 | G14: Official; Kessan Tanshin | H14: Consolidated statements | I14: FY2023 statement figures / FY2022 comparison.
A15: S11 | B15: FY2024 Financial Results | C15: Kessan Tanshin / final results | D15: FY2024 | E15: 2025 | F15: https://www.nttdata.com/global/en/-/media/nttdataglobal/1_files/investors/financial-results/2024/fy2024_fs_4q.pdf | G15: Official; Kessan Tanshin | H15: Consolidated statements / cash flow | I15: Exact FY2024 statement and cash-flow values.
... A24: S20 | B24: FY2024 Statutory Financial Statements / Notes | C24: Statutory note disclosure | D24: FY2024 | E24: 2025 | F24: https://www.nttdata.com/global/en/-/media/nttdataglobal/1_files/investors/stock-information/2025/web37_e.pdf?rev=2a93a0492d5b471ebd6d02c370fb6786 | G24: Official statutory disclosure | H24: Net sales / contract balances | I24: Contract assets ¥197,069mm; total contract liabilities ¥495,570mm; service-revenue breakdown.

Sheet Assumptions & Limitations
A1: Assumptions & Limitations
A2: Material comparability, definition, precision and missing-data issues. No hidden estimates.
A4: Issue | B4: Affected variable | C4: Affected year(s) | D4: Why the problem exists | E4: Treatment used | F4: Potential analytical impact | G4: Source ID
A5: JGAAP → IFRS transition | B5: All financial statements / account definitions | C5: FY2017–FY2018 | D5: Official archive splits JGAAP through FY2017 and IFRS from FY2018; some IFRS-restated FY2017 comparatives exist. | E5: Main series uses JGAAP FY2015–17 and IFRS FY2018+. IFRS-restated FY2017 is used only for contract balances and flagged. | F5: Cross-boundary ratios may reflect accounting changes as well as economics. | G5: S01
A6: Contract assets not a JGAAP main-series caption | B6: Contract assets | C6: FY2015–FY2017 | D6: Pre-IFRS reporting lacks the same contract-asset classification. | E6: FY2015–FY2016 left unavailable; FY2017 IFRS-restated closing balance shown only as bridge. | F6: Perfectly homogeneous contract-asset-day history cannot start in FY2015. | G6: S05
A7: Combined receivables | B7: Trade receivables | C7: IFRS years | D7: Balance sheet often shows trade and other receivables; pure trade AR requires notes. | E7: Pure trade AR used only when separately disclosed; combined balance kept separately; no split estimated. | F7: DSO should use pure AR only where isolated or a deliberately broader consistent definition. | G7: S12
A8: Combined payables | B8: Trade payables | C8: IFRS years | D8: Trade and other payables contains accrued and other liabilities. | E8: Pure trade AP used only where note breakdown exists; combined balance kept separately. | F8: Using combined payables mechanically would overstate supplier financing. | G8: S12
A9: FY2025 reposted balance-sheet definitions | B9: Receivables / contract assets; payables | C9: FY2024 comparative / FY2025 | D9: FY2025 presentation marks some breakdown items as reposted; FY2024 reposted comparisons do not reconcile to audited detailed captions. | E9: Audited FY2024 series remains intact; reposted FY2024/FY2025 rows are separate. | F9: Avoids a false apparent collapse/increase caused only by definition changes. | G9: S13
A10: FY2025 source precision | B10: Most FY2025 metrics | C10: FY2025 | D10: Presentation uses ¥bn to one decimal for many values. | E10: Mechanically multiplied by 1,000 to ¥mm and labelled rounded. | F10: Small FY2025 changes should not be overinterpreted. | G10: S13
A11: FY2025 detailed cash-flow gap | B11: CFO/CFI/CFF / WC movements | C11: FY2025 | D11: Detailed full-year CFS was not reliably extracted in this pass from the retrieved primary material. | E11: Cells remain N/A rather than estimated; ending cash and capital investment are captured. | F11: Retrieve current official data table before final FY2025 cash-conversion ratios. | G11: S14
A12: Dell Services acquisition | B12: Revenue; debt; AR; cash flow; backlog; mix | C12: FY2016 onward | D12: Large carve-out acquisition closed Nov. 2, 2016; acquisition cost ¥345.375bn and debt funding changed scale. | E12: Raw published data retained; event documented; no pro-forma history invented. | F12: FY2016–FY2017 trend changes are partly acquisition-driven. | G12: S16
A13: EMEA accounting-period alignment | B13: Revenue / orders | C13: FY2016 | D13: Some overseas accounting periods were unified, adding an extra period. | E13: Management-reported effect documented qualitatively; published totals retained. | F13: Year-over-year growth contains a calendar/consolidation effect. | G13: S03
A14: IFRS 16 lease accounting | B14: Lease liabilities / ROU assets / cash-flow classification | C14: FY2019 onward | D14: Lease liabilities and ROU assets become separately visible under IFRS 16-era reporting. | E14: Lease liabilities kept separate; no retroactive FY2018 estimate. | F14: Leverage and asset-intensity comparisons around FY2019 need caution. | G14: S06
A15: NTT Ltd. common-control combination | B15: Almost all balance-sheet and overseas metrics | C15: FY2022 onward | D15: Combination added very large receivables, payables, debt, PP&E, goodwill and NCI. | E15: Raw figures retained; acquired balances and event documented. | F15: FY2022 is a structural break, not ordinary working-capital growth. | G15: S12
... A22: FX detail not fully populated | B22: USD/JPY; EUR/JPY; constant currency | C22: FY2015–FY2025 | D22: FX is lower-priority for core working-capital build and varies by disclosure year. | E22: No FX conversion is performed; all raw amounts remain JPY. | F22: Geographic growth analysis should add FX data before constant-currency conclusions. | G22: S01

Sheet Model Setup
A1: Fiscal Year | B1: Accounting Basis | C1: Main Model | D1: Avg-Balance Ratios | E1: Structural Period | F1: Notes
A2: FY2015 | B2: JGAAP | C2: Context only | D2: No | E2: Historical | F2: Pre-IFRS
A3: FY2016 | B3: JGAAP | C3: Context only | D3: No | E3: Historical | F3: Dell Services acquisition
A4: FY2017 | B4: JGAAP | C4: Context only | D4: No | E4: Transition | F4: JGAAP→IFRS
A5: FY2018 | B5: IFRS | C5: Yes | D5: No / limited | E5: Pre-NTT Ltd. | F5: First IFRS year
A6: FY2019 | B6: IFRS | C6: Yes | D6: Yes | E6: Pre-NTT Ltd. | F6: Clean
A7: FY2020 | B7: IFRS | C7: Yes | D7: Yes | E7: Pre-NTT Ltd. | F7: Clean
A8: FY2021 | B8: IFRS | C8: Yes | D8: Yes | E8: Pre-NTT Ltd. | F8: Clean
A9: FY2022 | B9: IFRS | C9: Yes | D9: Yes, caution | E9: Transition | F9: NTT Ltd. combination
A10: FY2023 | B10: IFRS | C10: Yes | D10: Yes | E10: Post-NTT Ltd. | F10: Enlarged group
A11: FY2024 | B11: IFRS | C11: Yes | D11: Yes | E11: Post-NTT Ltd. | F11: Clean
A12: FY2025 | B12: IFRS | C12: Yes | D12: Partial | E12: Post-NTT Ltd. | F12: Some detailed data missing

Sheet Model
C2: NTT DATA — Phase 2 Working-Capital Model
C3: Formula-driven working-capital, operating-cycle and cash-conversion analysis (¥ million; days; percentages).
C4: Phase 2 complete. Strict definitions, valid-year chart helpers and visible FY2022 structural-break warnings are retained.
C6: Fiscal Year | D6: FY2018 | E6: FY2019 | F6: FY2020 | G6: FY2021 | H6: FY2022 | I6: FY2023 | J6: FY2024 | K6: FY2025 | M6: DATA QUALITY AND MODEL WARNINGS
C7: Period status | D7: Transition | E7: Normal | F7: Normal | G7: Normal | H7: Structural break | I7: Normal | J7: Partial | K7: Partial | M7: Issue | N7: Period(s) | O7: Model treatment
M8: First IFRS year | N8: FY2018 | O8: Do not average JGAAP and IFRS balances. Contract assets and total contract liabilities use explicit FY2017 IFRS-restated bridge values; other FY2018 averages remain unavailable.
C9: RAW MODEL INPUTS | M9: NTT Ltd. structural break | N9: FY2022 | O9: FY2022 Structural Break — NTT Ltd. consolidation. Average balance spans different consolidation scopes and should not be interpreted as an ordinary like-for-like operational change.
C10: Revenue | D10: =IF('NTT DATA Financials'!G6="","N/A — source data unavailable",'NTT DATA Financials'!G6) -> 2163625 | E10: =IF('NTT DATA Financials'!H6="","N/A — source data unavailable",'NTT DATA Financials'!H6) -> 2266808 | F10: =IF('NTT DATA Financials'!I6="","N/A — source data unavailable",'NTT DATA Financials'!I6) -> 2318658 | G10: =IF('NTT DATA Financials'!J6="","N/A — source data unavailable",'NTT DATA Financials'!J6) -> 2551906 | H10: =IF('NTT DATA Financials'!K6="","N/A — source data unavailable",'NTT DATA Financials'!K6) -> 3490182 | I10: =IF('NTT DATA Financials'!L6="","N/A — source data unavailable",'NTT DATA Financials'!L6) -> 4367387 | J10: =IF('NTT DATA Financials'!M6="","N/A — source data unavailable",'NTT DATA Financials'!M6) -> 4638721 | K10: =IF('NTT DATA Financials'!N6="","N/A — source data unavailable",'NTT DATA Financials'!N6) -> 5004600 | M10: FY2025 disclosure limitations | N10: FY2025 | O10: Pure trade receivables, separate contract assets, pure trade payables and total contract liabilities are unavailable. No split is estimated; only total inventory supports a FY2025 average.
C11: Cost of Sales | D11: =IF('NTT DATA Financials'!G7="","N/A — source data unavailable",'NTT DATA Financials'!G7) -> 1618636 | E11: =IF('NTT DATA Financials'!H7="","N/A — source data unavailable",'NTT DATA Financials'!H7) -> 1694577 | F11: =IF('NTT DATA Financials'!I7="","N/A — source data unavailable",'NTT DATA Financials'!I7) -> 1734083 | G11: =IF('NTT DATA Financials'!J7="","N/A — source data unavailable",'NTT DATA Financials'!J7) -> 1875904 | H11: =IF('NTT DATA Financials'!K7="","N/A — source data unavailable",'NTT DATA Financials'!K7) -> 2567948 | I11: =IF('NTT DATA Financials'!L7="","N/A — source data unavailable",'NTT DATA Financials'!L7) -> 3172421 | J11: =IF('NTT DATA Financials'!M7="","N/A — source data unavailable",'NTT DATA Financials'!M7) -> 3351333 | K11: =IF('NTT DATA Financials'!N7="","N/A — source data unavailable",'NTT DATA Financials'!N7) -> 3522200 | M11: Definition consistency | N11: All years | O11: Opening and closing balances must represent the same accounting and economic item.
C12: Trade Receivables — Pure | D12: =IF('Working Capital'!G6="","N/A — source data unavailable",'Working Capital'!G6) -> 489398 | E12: =IF('Working Capital'!H6="","N/A — source data unavailable",'Working Capital'!H6) -> 502994 | F12: =IF('Working Capital'!I6="","N/A — source data unavailable",'Working Capital'!I6) -> 517393 | G12: =IF('Working Capital'!J6="","N/A — source data unavailable",'Working Capital'!J6) -> 581302 | H12: =IF('Working Capital'!K6="","N/A — source data unavailable",'Working Capital'!K6) -> 1088978 | I12: =IF('Working Capital'!L6="","N/A — source data unavailable",'Working Capital'!L6) -> 1261976 | J12: =IF('Working Capital'!M6="","N/A — source data unavailable",'Working Capital'!M6) -> N/A — Insufficient public information to isolate reliably | K12: =IF('Working Capital'!N6="","N/A — source data unavailable",'Working Capital'!N6) -> N/A — Insufficient public information to isolate reliably | M12: Pure versus combined accounts | N12: All years | O12: Do not mix pure trade receivables or payables with combined trade-and-other balances or with receivables plus contract assets.
C13: Contract Assets — Separate | D13: =IF('Working Capital'!G13="","N/A — source data unavailable",'Working Capital'!G13) -> 81929 | E13: =IF('Working Capital'!H13="","N/A — source data unavailable",'Working Capital'!H13) -> 74828 | F13: =IF('Working Capital'!I13="","N/A — source data unavailable",'Working Capital'!I13) -> 101496 | G13: =IF('Working Capital'!J13="","N/A — source data unavailable",'Working Capital'!J13) -> 105477 | H13: =IF('Working Capital'!K13="","N/A — source data unavailable",'Working Capital'!K13) -> 123008 | I13: =IF('Working Capital'!L13="","N/A — source data unavailable",'Working Capital'!L13) -> 150738 | J13: =IF('Working Capital'!M13="","N/A — source data unavailable",'Working Capital'!M13) -> 197069 | K13: =IF('Working Capital'!N13="","N/A — source data unavailable",'Working Capital'!N13) -> N/A — Insufficient public information to isolate reliably | M13: Contract-liability scope | N13: All years | O13: Use total contract liabilities consistently. Do not substitute current contract liabilities for a missing total balance.
C14: Inventory — Total | D14: =IF('Working Capital'!G16="","N/A — source data unavailable",'Working Capital'!G16) -> 15294 | E14: =IF('Working Capital'!H16="","N/A — source data unavailable",'Working Capital'!H16) -> 13727 | F14: =IF('Working Capital'!I16="","N/A — source data unavailable",'Working Capital'!I16) -> 14476 | G14: =IF('Working Capital'!J16="","N/A — source data unavailable",'Working Capital'!J16) -> 25429 | H14: =IF('Working Capital'!K16="","N/A — source data unavailable",'Working Capital'!K16) -> 76221 | I14: =IF('Working Capital'!L16="","N/A — source data unavailable",'Working Capital'!L16) -> 51243 | J14: =IF('Working Capital'!M16="","N/A — source data unavailable",'Working Capital'!M16) -> 55900 | K14: =IF('Working Capital'!N16="","N/A — source data unavailable",'Working Capital'!N16) -> 69100 | M14: Phase 2 complete | N14: Steps 3–10 | O14: DSO, Contract Asset Days, DIO, DPO, Contract Liability Days, Traditional and Adjusted CCC, OWC and cash-conversion ratios are complete only for valid comparable years.
C15: Trade Payables — Pure | D15: =IF('Working Capital'!G21="","N/A — source data unavailable",'Working Capital'!G21) -> 144862 | E15: =IF('Working Capital'!H21="","N/A — source data unavailable",'Working Capital'!H21) -> 138224 | F15: =IF('Working Capital'!I21="","N/A — source data unavailable",'Working Capital'!I21) -> 154020 | G15: =IF('Working Capital'!J21="","N/A — source data unavailable",'Working Capital'!J21) -> 164617 | H15: =IF('Working Capital'!K21="","N/A — source data unavailable",'Working Capital'!K21) -> 399443 | I15: =IF('Working Capital'!L21="","N/A — source data unavailable",'Working Capital'!L21) -> 459825 | J15: =IF('Working Capital'!M21="","N/A — source data unavailable",'Working Capital'!M21) -> N/A — Insufficient public information to isolate reliably | K15: =IF('Working Capital'!N21="","N/A — source data unavailable",'Working Capital'!N21) -> N/A — Insufficient public information to isolate reliably
C16: Contract Liabilities — Total | D16: =IF('Working Capital'!G26="","N/A — source data unavailable",'Working Capital'!G26) -> 218774 | E16: =IF('Working Capital'!H26="","N/A — source data unavailable",'Working Capital'!H26) -> 256740 | F16: =IF('Working Capital'!I26="","N/A — source data unavailable",'Working Capital'!I26) -> 270224 | G16: =IF('Working Capital'!J26="","N/A — source data unavailable",'Working Capital'!J26) -> 283854 | H16: =IF('Working Capital'!K26="","N/A — source data unavailable",'Working Capital'!K26) -> 441816 | I16: =IF('Working Capital'!L26="","N/A — source data unavailable",'Working Capital'!L26) -> 506883 | J16: =IF('Working Capital'!M26="","N/A — source data unavailable",'Working Capital'!M26) -> 495570 | K16: =IF('Working Capital'!N26="","N/A — source data unavailable",'Working Capital'!N26) -> N/A — Insufficient public information to isolate reliably
M17: FORMULA CONVENTION
C18: IFRS-RESTATED OPENING BRIDGE INPUTS | M18: Cross-sheet source links | N18: Green font | O18: Phase 1 raw data feeds the model input rows.
C19: FY2017 IFRS-restated Contract Assets — FY2018 opening | D19: =IF('Working Capital'!F13="","N/A — source data unavailable",'Working Capital'!F13) -> 81948 | M19: Same-sheet calculations | N19: Black font | O19: Average formulas reference the model input rows.
C20: FY2017 IFRS-restated Contract Liabilities — FY2018 opening | D20: =IF('Working Capital'!F26="","N/A — source data unavailable",'Working Capital'!F26) -> 213791 | M20: Unavailable data | N20: Grey fill | O20: Missing or incomparable balances remain text, never zero.
M21: Structural break | N21: Amber fill | O21: FY2022 averages remain calculated but require caution.
C22: AVERAGE BALANCES
C23: Average Trade Receivables | D23: ="N/A — opening balance not sufficiently comparable" -> N/A — opening balance not sufficiently comparable | E23: =IF(AND(ISNUMBER(D12),ISNUMBER(E12)),AVERAGE(D12,E12),"N/A — insufficient comparable data") -> 496196 | F23: =IF(AND(ISNUMBER(E12),ISNUMBER(F12)),AVERAGE(E12,F12),"N/A — insufficient comparable data") -> 510193.5 | G23: =IF(AND(ISNUMBER(F12),ISNUMBER(G12)),AVERAGE(F12,G12),"N/A — insufficient comparable data") -> 549347.5 | H23: =IF(AND(ISNUMBER(G12),ISNUMBER(H12)),AVERAGE(G12,H12),"N/A — insufficient comparable data") -> 835140 | I23: =IF(AND(ISNUMBER(H12),ISNUMBER(I12)),AVERAGE(H12,I12),"N/A — insufficient comparable data") -> 1175477 | J23: =IF(AND(ISNUMBER(I12),ISNUMBER(J12)),AVERAGE(I12,J12),"N/A — insufficient comparable disclosure") -> N/A — insufficient comparable disclosure | K23: =IF(AND(ISNUMBER(J12),ISNUMBER(K12)),AVERAGE(J12,K12),"N/A — insufficient comparable disclosure") -> N/A — insufficient comparable disclosure
C24: Average Contract Assets | D24: =IF(AND(ISNUMBER(D19),ISNUMBER(D13)),AVERAGE(D19,D13),"N/A — insufficient comparable data") -> 81938.5 | E24: =IF(AND(ISNUMBER(D13),ISNUMBER(E13)),AVERAGE(D13,E13),"N/A — insufficient comparable data") -> 78378.5 | F24: =IF(AND(ISNUMBER(E13),ISNUMBER(F13)),AVERAGE(E13,F13),"N/A — insufficient comparable data") -> 88162 | G24: =IF(AND(ISNUMBER(F13),ISNUMBER(G13)),AVERAGE(F13,G13),"N/A — insufficient comparable data") -> 103486.5 | H24: =IF(AND(ISNUMBER(G13),ISNUMBER(H13)),AVERAGE(G13,H13),"N/A — insufficient comparable data") -> 114242.5 | I24: =IF(AND(ISNUMBER(H13),ISNUMBER(I13)),AVERAGE(H13,I13),"N/A — insufficient comparable data") -> 136873 | J24: =IF(AND(ISNUMBER(I13),ISNUMBER(J13)),AVERAGE(I13,J13),"N/A — insufficient comparable disclosure") -> 173903.5 | K24: =IF(AND(ISNUMBER(J13),ISNUMBER(K13)),AVERAGE(J13,K13),"N/A — insufficient comparable disclosure") -> N/A — insufficient comparable disclosure | M24: DSO INTERPRETATION AND WARNINGS
C25: Average Inventory | D25: ="N/A — opening balance not sufficiently comparable" -> N/A — opening balance not sufficiently comparable | E25: =IF(AND(ISNUMBER(D14),ISNUMBER(E14)),AVERAGE(D14,E14),"N/A — insufficient comparable data") -> 14510.5 | F25: =IF(AND(ISNUMBER(E14),ISNUMBER(F14)),AVERAGE(E14,F14),"N/A — insufficient comparable data") -> 14101.5 | G25: =IF(AND(ISNUMBER(F14),ISNUMBER(G14)),AVERAGE(F14,G14),"N/A — insufficient comparable data") -> 19952.5 | H25: =IF(AND(ISNUMBER(G14),ISNUMBER(H14)),AVERAGE(G14,H14),"N/A — insufficient comparable data") -> 50825 | I25: =IF(AND(ISNUMBER(H14),ISNUMBER(I14)),AVERAGE(H14,I14),"N/A — insufficient comparable data") -> 63732 | J25: =IF(AND(ISNUMBER(I14),ISNUMBER(J14)),AVERAGE(I14,J14),"N/A — insufficient comparable disclosure") -> 53571.5 | K25: =IF(AND(ISNUMBER(J14),ISNUMBER(K14)),AVERAGE(J14,K14),"N/A — insufficient comparable disclosure") -> 62500 | M25: Issue | N25: Period(s) | O25: Interpretation / treatment
C26: Average Trade Payables | D26: ="N/A — opening balance not sufficiently comparable" -> N/A — opening balance not sufficiently comparable | E26: =IF(AND(ISNUMBER(D15),ISNUMBER(E15)),AVERAGE(D15,E15),"N/A — insufficient comparable data") -> 141543 | F26: =IF(AND(ISNUMBER(E15),ISNUMBER(F15)),AVERAGE(E15,F15),"N/A — insufficient comparable data") -> 146122 | G26: =IF(AND(ISNUMBER(F15),ISNUMBER(G15)),AVERAGE(F15,G15),"N/A — insufficient comparable data") -> 159318.5 | H26: =IF(AND(ISNUMBER(G15),ISNUMBER(H15)),AVERAGE(G15,H15),"N/A — insufficient comparable data") -> 282030 | I26: =IF(AND(ISNUMBER(H15),ISNUMBER(I15)),AVERAGE(H15,I15),"N/A — insufficient comparable data") -> 429634 | J26: =IF(AND(ISNUMBER(I15),ISNUMBER(J15)),AVERAGE(I15,J15),"N/A — insufficient comparable disclosure") -> N/A — insufficient comparable disclosure | K26: =IF(AND(ISNUMBER(J15),ISNUMBER(K15)),AVERAGE(J15,K15),"N/A — insufficient comparable disclosure") -> N/A — insufficient comparable disclosure | M26: DSO definition | N26: Valid years | O26: DSO measures invoiced-but-uncollected receivables relative to annual revenue. It does not capture cash tied up before invoicing in contract assets. Contract Asset Days will be analysed separately in Step 4.
C27: Average Contract Liabilities | D27: =IF(AND(ISNUMBER(D20),ISNUMBER(D16)),AVERAGE(D20,D16),"N/A — insufficient comparable data") -> 216282.5 | E27: =IF(AND(ISNUMBER(D16),ISNUMBER(E16)),AVERAGE(D16,E16),"N/A — insufficient comparable data") -> 237757 | F27: =IF(AND(ISNUMBER(E16),ISNUMBER(F16)),AVERAGE(E16,F16),"N/A — insufficient comparable data") -> 263482 | G27: =IF(AND(ISNUMBER(F16),ISNUMBER(G16)),AVERAGE(F16,G16),"N/A — insufficient comparable data") -> 277039 | H27: =IF(AND(ISNUMBER(G16),ISNUMBER(H16)),AVERAGE(G16,H16),"N/A — insufficient comparable data") -> 362835 | I27: =IF(AND(ISNUMBER(H16),ISNUMBER(I16)),AVERAGE(H16,I16),"N/A — insufficient comparable data") -> 474349.5 | J27: =IF(AND(ISNUMBER(I16),ISNUMBER(J16)),AVERAGE(I16,J16),"N/A — insufficient comparable disclosure") -> 501226.5 | K27: =IF(AND(ISNUMBER(J16),ISNUMBER(K16)),AVERAGE(J16,K16),"N/A — insufficient comparable disclosure") -> N/A — insufficient comparable disclosure | M27: NTT Ltd. structural break | N27: FY2022 | O27: Structural break — NTT Ltd. consolidation / business combination. Average receivables span materially different consolidation scopes. Interpret with caution.
M28: Unavailable DSO | N28: FY2024–FY2025 | O28: DSO is unavailable under the strict pure-trade-receivable definition because comparable pure trade receivables cannot be reliably isolated. Combined receivable captions are not substituted.
C29: EFFICIENCY METRICS | M29: Preliminary observation | N29: FY2019–FY2023 | O29: Pre-NTT Ltd., reported DSO was relatively stable around 79–80 days from FY2019–FY2021. Reported DSO then increased in FY2022–FY2023. FY2022 onward is affected by the NTT Ltd. structural change, so the increase cannot yet be attributed solely to weaker collection efficiency.
C30: Days Sales Outstanding (DSO) | D30: ="N/A — insufficient comparable opening balance" -> N/A — insufficient comparable opening balance | E30: =IF(AND(ISNUMBER(E23),ISNUMBER(E10),E10<>0),E23/E10*365,"N/A — insufficient comparable data") -> 79.897168 | F30: =IF(AND(ISNUMBER(F23),ISNUMBER(F10),F10<>0),F23/F10*365,"N/A — insufficient comparable data") -> 80.313969 | G30: =IF(AND(ISNUMBER(G23),ISNUMBER(G10),G10<>0),G23/G10*365,"N/A — insufficient comparable data") -> 78.573363 | H30: =IF(AND(ISNUMBER(H23),ISNUMBER(H10),H10<>0),H23/H10*365,"N/A — insufficient comparable data") -> 87.338167 | I30: =IF(AND(ISNUMBER(I23),ISNUMBER(I10),I10<>0),I23/I10*365,"N/A — insufficient comparable data") -> 98.239314 | J30: =IF(AND(ISNUMBER(J23),ISNUMBER(J10),J10<>0),J23/J10*365,"N/A — insufficient comparable disclosure") -> N/A — insufficient comparable disclosure | K30: =IF(AND(ISNUMBER(K23),ISNUMBER(K10),K10<>0),K23/K10*365,"N/A — insufficient comparable disclosure") -> N/A — insufficient comparable disclosure
C31: Contract Asset Days | D31: =IF(AND(ISNUMBER(D24),ISNUMBER(D10),D10<>0),D24/D10*365,"N/A — insufficient comparable data") -> 13.822891 | E31: =IF(AND(ISNUMBER(E24),ISNUMBER(E10),E10<>0),E24/E10*365,"N/A — insufficient comparable data") -> 12.620457 | F31: =IF(AND(ISNUMBER(F24),ISNUMBER(F10),F10<>0),F24/F10*365,"N/A — insufficient comparable data") -> 13.878343 | G31: =IF(AND(ISNUMBER(G24),ISNUMBER(G10),G10<>0),G24/G10*365,"N/A — insufficient comparable data") -> 14.80171 | H31: =IF(AND(ISNUMBER(H24),ISNUMBER(H10),H10<>0),H24/H10*365,"N/A — insufficient comparable data") -> 11.947375 | I31: =IF(AND(ISNUMBER(I24),ISNUMBER(I10),I10<>0),I24/I10*365,"N/A — insufficient comparable data") -> 11.439024 | J31: =IF(AND(ISNUMBER(J24),ISNUMBER(J10),J10<>0),J24/J10*365,"N/A — insufficient comparable data") -> 13.683681 | K31: =IF(AND(ISNUMBER(K24),ISNUMBER(K10),K10<>0),K24/K10*365,"N/A — insufficient comparable disclosure") -> N/A — insufficient comparable disclosure | M31: DSO CHART DATA — VALID YEARS ONLY
C32: Days Inventory Outstanding (DIO) | D32: ="N/A — opening balance not sufficiently comparable" -> N/A — opening balance not sufficiently comparable | E32: =IF(AND(ISNUMBER(E25),ISNUMBER(E11),E11<>0),E25/E11*365,"N/A — insufficient comparable data") -> 3.1254599 | F32: =IF(AND(ISNUMBER(F25),ISNUMBER(F11),F11<>0),F25/F11*365,"N/A — insufficient comparable data") -> 2.9681667 | G32: =IF(AND(ISNUMBER(G25),ISNUMBER(G11),G11<>0),G25/G11*365,"N/A — insufficient comparable data") -> 3.8822149 | H32: =IF(AND(ISNUMBER(H25),ISNUMBER(H11),H11<>0),H25/H11*365,"N/A — insufficient comparable data") -> 7.2241046 | I32: =IF(AND(ISNUMBER(I25),ISNUMBER(I11),I11<>0),I25/I11*365,"N/A — insufficient comparable data") -> 7.332627 | J32: =IF(AND(ISNUMBER(J25),ISNUMBER(J11),J11<>0),J25/J11*365,"N/A — insufficient comparable data") -> 5.8345731 | K32: =IF(AND(ISNUMBER(K25),ISNUMBER(K11),K11<>0),K25/K11*365,"N/A — insufficient comparable data") -> 6.4767759 | M32: Fiscal Year | N32: DSO
C33: Days Payables Outstanding (DPO) | D33: =IF(AND(ISNUMBER(D26),ISNUMBER(D11),D11<>0),D26/D11*365,"N/A — opening balance not sufficiently comparable") -> N/A — opening balance not sufficiently comparable | E33: =IF(AND(ISNUMBER(E26),ISNUMBER(E11),E11<>0),E26/E11*365,"N/A — insufficient comparable data") -> 30.487369 | F33: =IF(AND(ISNUMBER(F26),ISNUMBER(F11),F11<>0),F26/F11*365,"N/A — insufficient comparable data") -> 30.756619 | G33: =IF(AND(ISNUMBER(G26),ISNUMBER(G11),G11<>0),G26/G11*365,"N/A — insufficient comparable data") -> 30.999056 | H33: =IF(AND(ISNUMBER(H26),ISNUMBER(H11),H11<>0),H26/H11*365,"N/A — insufficient comparable data") -> 40.086851 | I33: =IF(AND(ISNUMBER(I26),ISNUMBER(I11),I11<>0),I26/I11*365,"N/A — insufficient comparable data") -> 49.431147 | J33: =IF(AND(ISNUMBER(J26),ISNUMBER(J11),J11<>0),J26/J11*365,"N/A — insufficient comparable disclosure") -> N/A — insufficient comparable disclosure | K33: =IF(AND(ISNUMBER(K26),ISNUMBER(K11),K11<>0),K26/K11*365,"N/A — insufficient comparable disclosure") -> N/A — insufficient comparable disclosure | M33: =E$6 -> FY2019 | N33: =E30 -> 79.897168
C34: Contract Liability Days | D34: =IF(AND(ISNUMBER(D27),ISNUMBER(D10),D10<>0),D27/D10*365,"N/A — insufficient comparable data") -> 36.486504 | E34: =IF(AND(ISNUMBER(E27),ISNUMBER(E10),E10<>0),E27/E10*365,"N/A — insufficient comparable data") -> 38.283483 | F34: =IF(AND(ISNUMBER(F27),ISNUMBER(F10),F10<>0),F27/F10*365,"N/A — insufficient comparable data") -> 41.476979 | G34: =IF(AND(ISNUMBER(G27),ISNUMBER(G10),G10<>0),G27/G10*365,"N/A — insufficient comparable data") -> 39.624984 | H34: =IF(AND(ISNUMBER(H27),ISNUMBER(H10),H10<>0),H27/H10*365,"N/A — insufficient comparable data") -> 37.944948 | I34: =IF(AND(ISNUMBER(I27),ISNUMBER(I10),I10<>0),I27/I10*365,"N/A — insufficient comparable data") -> 39.643285 | J34: =IF(AND(ISNUMBER(J27),ISNUMBER(J10),J10<>0),J27/J10*365,"N/A — insufficient comparable data") -> 39.439249 | K34: =IF(AND(ISNUMBER(K27),ISNUMBER(K10),K10<>0),K27/K10*365,"N/A — insufficient comparable disclosure") -> N/A — insufficient comparable disclosure | M34: =F$6 -> FY2020 | N34: =F30 -> 80.313969
C35: FY2022: structural break — NTT Ltd. consolidation / business combination | M35: =G$6 -> FY2021 | N35: =G30 -> 78.573363
M36: =H$6 -> FY2022 | N36: =H30 -> 87.338167
M37: =I$6 -> FY2023 | N37: =I30 -> 98.239314
M39: CONTRACT ASSET DAYS INTERPRETATION AND WARNINGS
M40: Issue | N40: Period(s) | O40: Interpretation / treatment
M41: Methodology | N41: Valid years | O41: Contract Asset Days measures average contract assets relative to annual revenue. It approximates how much annual revenue is tied up in work already performed but not yet converted into unconditional trade receivables.
M42: IFRS opening bridge | N42: FY2018 | O42: FY2018 uses an explicitly disclosed IFRS-restated FY2017 contract-asset balance as the opening balance.
M43: NTT Ltd. structural break | N43: FY2022 | O43: Structural break — NTT Ltd. consolidation / business combination. Average Contract Assets spans materially different consolidation scopes. Interpret with caution.
M44: Unavailable Contract Asset Days | N44: FY2025 | O44: FY2025 is unavailable because a separate comparable Contract Assets closing balance cannot be reliably isolated from the broader disclosed category. No split is estimated.
M45: Customer-side diagnostic | N45: Overlapping years | O45: DSO measures post-invoice receivables timing. Contract Asset Days measures pre-invoice / pre-unconditional receivable timing. DSO is substantially larger over the overlapping years, but the metrics remain separately reported.
M46: Preliminary observation | N46: FY2018–FY2024 | O46: Contract Asset Days remained within a relatively narrow range over FY2018–FY2024, broadly around 11–15 days. The metric declined after the FY2022 structural change before rising again in FY2024. This suggests that the large increase previously observed in DSO is not mirrored by an equally large increase in Contract Asset Days.
M48: CONTRACT ASSET DAYS CHART DATA — VALID YEARS ONLY
M49: Fiscal Year | N49: Contract Asset Days
M50: =D$6 -> FY2018 | N50: =D31 -> 13.822891
M51: =E$6 -> FY2019 | N51: =E31 -> 12.620457
M52: =F$6 -> FY2020 | N52: =F31 -> 13.878343
M53: =G$6 -> FY2021 | N53: =G31 -> 14.80171
C54: FY2022: structural break — NTT Ltd. consolidation / business combination | M54: =H$6 -> FY2022 | N54: =H31 -> 11.947375
M55: =I$6 -> FY2023 | N55: =I31 -> 11.439024
M56: =J$6 -> FY2024 | N56: =J31 -> 13.683681
M58: DIO INTERPRETATION AND WARNINGS
M59: Issue | N59: Period(s) | O59: Interpretation / treatment
M60: Methodology | N60: Valid years | O60: DIO measures average inventory relative to annual Cost of Sales. It approximates how many days of the cost base are tied up in inventory.
M61: Unavailable DIO | N61: FY2018 | O61: FY2018 remains unavailable because a sufficiently comparable opening IFRS inventory balance is not used under the current model.
M62: NTT Ltd. structural break | N62: FY2022 | O62: Structural break — NTT Ltd. consolidation materially changed group scope and inventory base. Interpret with caution. No pro-forma inventory balance is estimated.
M63: Preliminary observation | N63: FY2019–FY2025 | O63: DIO was relatively low at approximately 3–4 days during FY2019–FY2021, increased to roughly 7 days in FY2022–FY2023, and then moderated somewhat. Despite the increase, inventory remains a comparatively small component of NTT DATA's operating cycle relative to receivables.
M65: DIO CHART DATA — VALID YEARS ONLY
M66: Fiscal Year | N66: DIO
M67: =E$6 -> FY2019 | N67: =E32 -> 3.1254599
M68: =F$6 -> FY2020 | N68: =F32 -> 2.9681667
M69: =G$6 -> FY2021 | N69: =G32 -> 3.8822149
M70: =H$6 -> FY2022 | N70: =H32 -> 7.2241046
M71: =I$6 -> FY2023 | N71: =I32 -> 7.332627
M72: =J$6 -> FY2024 | N72: =J32 -> 5.8345731
C73: FY2022: structural break — NTT Ltd. consolidation / business combination | M73: =K$6 -> FY2025 | N73: =K32 -> 6.4767759
M75: DPO INTERPRETATION AND WARNINGS
M76: Issue | N76: Period(s) | O76: Interpretation / treatment
M77: Methodology | N77: Valid years | O77: DPO uses Average Trade Payables divided by Cost of Sales × 365. It approximates the number of annual cost-of-sales days funded by unpaid pure trade payables.
M78: Strict payable definition | N78: All years | O78: Only pure trade payables feed the numerator. Trade and other payables, accrued expenses and other combined liabilities are not substituted.
M79: NTT Ltd. structural break | N79: FY2022 | O79: Structural break — NTT Ltd. consolidation / business combination. The average spans materially different group scopes; no pro-forma balance is estimated.
M80: Availability and preliminary observation | N80: FY2019–FY2023 | O80: DPO is available only from FY2019 through FY2023. It was about 30–31 days through FY2021, then increased to roughly 40 days in FY2022 and 49 days in FY2023. The higher supplier-funding signal requires caution around the structural change and is not automatically positive.
M82: CONTRACT LIABILITY DAYS INTERPRETATION AND WARNINGS
M83: Issue | N83: Period(s) | O83: Interpretation / treatment
M84: Methodology | N84: Valid years | O84: Contract Liability Days uses Average Contract Liabilities divided by Revenue × 365. It approximates customer advance funding relative to annual revenue.
M85: IFRS opening bridge | N85: FY2018 | O85: FY2018 uses the explicit FY2017 IFRS-restated total contract-liability balance as its opening input. JGAAP advances received are not used.
M86: Total versus current scope | N86: All years | O86: The model uses total contract liabilities consistently. Current contract liabilities are not substituted to extend FY2025.
M87: NTT Ltd. structural break | N87: FY2022 | O87: Structural break — NTT Ltd. consolidation / business combination. The average spans materially different scopes and should be interpreted cautiously.
M88: Availability and preliminary observation | N88: FY2018–FY2024 | O88: Contract Liability Days stayed broadly in the high-30s to low-40s. Customer advances therefore provide a material and relatively steady operating-cycle funding offset. FY2025 is unavailable because comparable total contract liabilities are not isolated.
M91: CCC INTERPRETATION AND WARNINGS
C92: AGGREGATE METRICS | M92: Issue | N92: Period(s) | O92: Interpretation / treatment
C93: Traditional Cash Conversion Cycle (CCC) | D93: =IF(AND(ISNUMBER(D30),ISNUMBER(D32),ISNUMBER(D33)),D30+D32-D33,"N/A — incomplete comparable components") -> N/A — incomplete comparable components | E93: =IF(AND(ISNUMBER(E30),ISNUMBER(E32),ISNUMBER(E33)),E30+E32-E33,"N/A — incomplete comparable components") -> 52.535259 | F93: =IF(AND(ISNUMBER(F30),ISNUMBER(F32),ISNUMBER(F33)),F30+F32-F33,"N/A — incomplete comparable components") -> 52.525517 | G93: =IF(AND(ISNUMBER(G30),ISNUMBER(G32),ISNUMBER(G33)),G30+G32-G33,"N/A — incomplete comparable components") -> 51.456523 | H93: =IF(AND(ISNUMBER(H30),ISNUMBER(H32),ISNUMBER(H33)),H30+H32-H33,"N/A — incomplete comparable components") -> 54.475421 | I93: =IF(AND(ISNUMBER(I30),ISNUMBER(I32),ISNUMBER(I33)),I30+I32-I33,"N/A — incomplete comparable components") -> 56.140794 | J93: =IF(AND(ISNUMBER(J30),ISNUMBER(J32),ISNUMBER(J33)),J30+J32-J33,"N/A — incomplete comparable components") -> N/A — incomplete comparable components | K93: =IF(AND(ISNUMBER(K30),ISNUMBER(K32),ISNUMBER(K33)),K30+K32-K33,"N/A — incomplete comparable components") -> N/A — incomplete comparable components | M93: Strict complete-component rule | N93: All years | O93: Traditional CCC is calculated only where DSO, DIO and DPO are all valid. Adjusted CCC is calculated only where all five validated days components are valid; missing metrics are never treated as zero.
C94: Adjusted Cash Conversion Cycle | D94: =IF(AND(ISNUMBER(D30),ISNUMBER(D31),ISNUMBER(D32),ISNUMBER(D33),ISNUMBER(D34)),D30+D31+D32-D33-D34,"N/A — incomplete comparable components") -> N/A — incomplete comparable components | E94: =IF(AND(ISNUMBER(E30),ISNUMBER(E31),ISNUMBER(E32),ISNUMBER(E33),ISNUMBER(E34)),E30+E31+E32-E33-E34,"N/A — incomplete comparable components") -> 26.872233 | F94: =IF(AND(ISNUMBER(F30),ISNUMBER(F31),ISNUMBER(F32),ISNUMBER(F33),ISNUMBER(F34)),F30+F31+F32-F33-F34,"N/A — incomplete comparable components") -> 24.92688 | G94: =IF(AND(ISNUMBER(G30),ISNUMBER(G31),ISNUMBER(G32),ISNUMBER(G33),ISNUMBER(G34)),G30+G31+G32-G33-G34,"N/A — incomplete comparable components") -> 26.633248 | H94: =IF(AND(ISNUMBER(H30),ISNUMBER(H31),ISNUMBER(H32),ISNUMBER(H33),ISNUMBER(H34)),H30+H31+H32-H33-H34,"N/A — incomplete comparable components") -> 28.477847 | I94: =IF(AND(ISNUMBER(I30),ISNUMBER(I31),ISNUMBER(I32),ISNUMBER(I33),ISNUMBER(I34)),I30+I31+I32-I33-I34,"N/A — incomplete comparable components") -> 27.936533 | J94: =IF(AND(ISNUMBER(J30),ISNUMBER(J31),ISNUMBER(J32),ISNUMBER(J33),ISNUMBER(J34)),J30+J31+J32-J33-J34,"N/A — incomplete comparable components") -> N/A — incomplete comparable components | K94: =IF(AND(ISNUMBER(K30),ISNUMBER(K31),ISNUMBER(K32),ISNUMBER(K33),ISNUMBER(K34)),K30+K31+K32-K33-K34,"N/A — incomplete comparable components") -> N/A — incomplete comparable components | M94: Comparable window | N94: FY2019–FY2023 | O94: Both CCC measures have the same shortened comparable window because pure trade receivables and payables are required.
C95: FY2022: structural break — NTT Ltd. consolidation / business combination | M95: NTT Ltd. structural break | N95: FY2022 | O95: Structural break — NTT Ltd. consolidation / business combination. FY2022 and post-combination changes cannot be attributed solely to ordinary operating execution.
M96: Standalone interpretation | N96: Valid years | O96: Traditional CCC increased modestly after FY2021, while Adjusted CCC stayed broadly in the mid-to-high 20-day range because supplier financing and customer advances offset much of the customer-side cash tie-up. Peer-relative judgement is deferred to Phase 3.
C98: OPERATING WORKING CAPITAL — CLOSING BALANCES (¥ million) | M98: OWC METHODOLOGY AND WARNINGS
C99: ="Fiscal Year" -> Fiscal Year | D99: =D$6 -> FY2018 | E99: =E$6 -> FY2019 | F99: =F$6 -> FY2020 | G99: =G$6 -> FY2021 | H99: =H$6 -> FY2022 | I99: =I$6 -> FY2023 | J99: =J$6 -> FY2024 | K99: =K$6 -> FY2025 | M99: Issue | N99: Period(s) | O99: Interpretation / treatment
C100: Trade Receivables — Pure | D100: =D12 -> 489398 | E100: =E12 -> 502994 | F100: =F12 -> 517393 | G100: =G12 -> 581302 | H100: =H12 -> 1088978 | I100: =I12 -> 1261976 | J100: =J12 -> N/A — Insufficient public information to isolate reliably | K100: =K12 -> N/A — Insufficient public information to isolate reliably | M100: Definition | N100: Valid years | O100: OWC equals closing pure Trade Receivables + separate Contract Assets + total Inventory − pure Trade Payables − total Contract Liabilities. Average balances are not used for this point-in-time stock.
C101: Contract Assets — Separate | D101: =D13 -> 81929 | E101: =E13 -> 74828 | F101: =F13 -> 101496 | G101: =G13 -> 105477 | H101: =H13 -> 123008 | I101: =I13 -> 150738 | J101: =J13 -> 197069 | K101: =K13 -> N/A — Insufficient public information to isolate reliably | M101: Strict completeness | N101: All years | O101: If any of the five closing components is unavailable, OWC and OWC / Revenue remain unavailable. Combined receivable or payable captions are not substituted.
C102: Inventory — Total | D102: =D14 -> 15294 | E102: =E14 -> 13727 | F102: =F14 -> 14476 | G102: =G14 -> 25429 | H102: =H14 -> 76221 | I102: =I14 -> 51243 | J102: =J14 -> 55900 | K102: =K14 -> 69100 | M102: NTT Ltd. structural break | N102: FY2022 | O102: Structural break — NTT Ltd. consolidation / business combination. The FY2022 step-up reflects a materially enlarged group as well as operating movements.
C103: less: Trade Payables — Pure | D103: =D15 -> 144862 | E103: =E15 -> 138224 | F103: =F15 -> 154020 | G103: =G15 -> 164617 | H103: =H15 -> 399443 | I103: =I15 -> 459825 | J103: =J15 -> N/A — Insufficient public information to isolate reliably | K103: =K15 -> N/A — Insufficient public information to isolate reliably | M103: Comparable window | N103: FY2018–FY2023 | O103: OWC and OWC / Revenue are valid through FY2023 only. FY2024–FY2025 lack isolated pure trade receivables and pure trade payables.
C104: less: Contract Liabilities — Total | D104: =D16 -> 218774 | E104: =E16 -> 256740 | F104: =F16 -> 270224 | G104: =G16 -> 283854 | H104: =H16 -> 441816 | I104: =I16 -> 506883 | J104: =J16 -> 495570 | K104: =K16 -> N/A — Insufficient public information to isolate reliably | M104: Preliminary direction | N104: Valid years | O104: Absolute OWC increased materially by FY2022–FY2023. OWC / Revenue rose to about 12.8% in FY2022 and eased to about 11.4% in FY2023; the structural break limits attribution.
C105: Operating Working Capital | D105: =IF(AND(ISNUMBER(D100),ISNUMBER(D101),ISNUMBER(D102),ISNUMBER(D103),ISNUMBER(D104)),D100+D101+D102-D103-D104,"N/A — incomplete comparable operating working-capital components") -> 222985 | E105: =IF(AND(ISNUMBER(E100),ISNUMBER(E101),ISNUMBER(E102),ISNUMBER(E103),ISNUMBER(E104)),E100+E101+E102-E103-E104,"N/A — incomplete comparable operating working-capital components") -> 196585 | F105: =IF(AND(ISNUMBER(F100),ISNUMBER(F101),ISNUMBER(F102),ISNUMBER(F103),ISNUMBER(F104)),F100+F101+F102-F103-F104,"N/A — incomplete comparable operating working-capital components") -> 209121 | G105: =IF(AND(ISNUMBER(G100),ISNUMBER(G101),ISNUMBER(G102),ISNUMBER(G103),ISNUMBER(G104)),G100+G101+G102-G103-G104,"N/A — incomplete comparable operating working-capital components") -> 263737 | H105: =IF(AND(ISNUMBER(H100),ISNUMBER(H101),ISNUMBER(H102),ISNUMBER(H103),ISNUMBER(H104)),H100+H101+H102-H103-H104,"N/A — incomplete comparable operating working-capital components") -> 446948 | I105: =IF(AND(ISNUMBER(I100),ISNUMBER(I101),ISNUMBER(I102),ISNUMBER(I103),ISNUMBER(I104)),I100+I101+I102-I103-I104,"N/A — incomplete comparable operating working-capital components") -> 497249 | J105: =IF(AND(ISNUMBER(J100),ISNUMBER(J101),ISNUMBER(J102),ISNUMBER(J103),ISNUMBER(J104)),J100+J101+J102-J103-J104,"N/A — incomplete comparable operating working-capital components") -> N/A — incomplete comparable operating working-capital components | K105: =IF(AND(ISNUMBER(K100),ISNUMBER(K101),ISNUMBER(K102),ISNUMBER(K103),ISNUMBER(K104)),K100+K101+K102-K103-K104,"N/A — incomplete comparable operating working-capital components") -> N/A — incomplete comparable operating working-capital components
C106: Revenue | D106: =D10 -> 2163625 | E106: =E10 -> 2266808 | F106: =F10 -> 2318658 | G106: =G10 -> 2551906 | H106: =H10 -> 3490182 | I106: =I10 -> 4367387 | J106: =J10 -> 4638721 | K106: =K10 -> 5004600
C107: OWC / Revenue | D107: =IF(AND(ISNUMBER(D105),ISNUMBER(D106),D106<>0),D105/D106,"N/A — incomplete comparable operating working-capital components") -> 0.10306084 | E107: =IF(AND(ISNUMBER(E105),ISNUMBER(E106),E106<>0),E105/E106,"N/A — incomplete comparable operating working-capital components") -> 0.086723269 | F107: =IF(AND(ISNUMBER(F105),ISNUMBER(F106),F106<>0),F105/F106,"N/A — incomplete comparable operating working-capital components") -> 0.090190533 | G107: =IF(AND(ISNUMBER(G105),ISNUMBER(G106),G106<>0),G105/G106,"N/A — incomplete comparable operating working-capital components") -> 0.10334903 | H107: =IF(AND(ISNUMBER(H105),ISNUMBER(H106),H106<>0),H105/H106,"N/A — incomplete comparable operating working-capital components") -> 0.12805865 | I107: =IF(AND(ISNUMBER(I105),ISNUMBER(I106),I106<>0),I105/I106,"N/A — incomplete comparable operating working-capital components") -> 0.11385504 | J107: =IF(AND(ISNUMBER(J105),ISNUMBER(J106),J106<>0),J105/J106,"N/A — incomplete comparable operating working-capital components") -> N/A — incomplete comparable operating working-capital components | K107: =IF(AND(ISNUMBER(K105),ISNUMBER(K106),K106<>0),K105/K106,"N/A — incomplete comparable operating working-capital components") -> N/A — incomplete comparable operating working-capital components | M107: CASH CONVERSION METHODOLOGY AND WARNINGS
M108: Issue | N108: Period(s) | O108: Interpretation / treatment
M109: Reported numerator | N109: FY2018–FY2024 | O109: All three ratios use reported cash flow from operating activities. No cash-flow proxy is used.
C110: CASH CONVERSION INPUTS (¥ million) | M110: CFO / EBITDA | N110: Valid years | O110: Uses the officially reported EBITDA KPI as the denominator; it is not an analyst reconstruction.
C111: ="Fiscal Year" -> Fiscal Year | D111: =D$6 -> FY2018 | E111: =E$6 -> FY2019 | F111: =F$6 -> FY2020 | G111: =G$6 -> FY2021 | H111: =H$6 -> FY2022 | I111: =I$6 -> FY2023 | J111: =J$6 -> FY2024 | K111: =K$6 -> FY2025 | M111: CFO / Operating Profit | N111: Valid years | O111: Uses the company's reported Operating Profit. It is labelled exactly and is not renamed EBIT.
...

Sheet Summary
A1: NTT DATA — Phase 2 Working-Capital and Cash-Conversion Summary
A2: Standalone analysis; IFRS-era years shown only where definitions and source availability are comparable. | S2: CASH CONVERSION CHART DATA — VALID YEARS ONLY
S3: Fiscal Year | T3: CFO / EBITDA | U3: CFO / Operating Profit | V3: CFO / Net Income
A4: A. KEY METRICS TABLE | J4: B. KEY FINDINGS | S4: =Model!D6 -> FY2018 | T4: =Model!D118 -> 0.7846952 | U4: =Model!D119 -> 1.6382789 | V4: =Model!D120 -> 2.4768689
A5: ="Metric" -> Metric | B5: =Model!D6 -> FY2018 | C5: =Model!E6 -> FY2019 | D5: =Model!F6 -> FY2020 | E5: =Model!G6 -> FY2021 | F5: =Model!H6 -> FY2022 | G5: =Model!I6 -> FY2023 | H5: =Model!J6 -> FY2024 | I5: =Model!K6 -> FY2025 | J5: Area | K5: Evidence-based takeaway | S5: =Model!E6 -> FY2019 | T5: =Model!E118 -> 0.94690565 | U5: =Model!E119 -> 2.138433 | V5: =Model!E120 -> 3.5100035
A6: Days Sales Outstanding (DSO) | B6: =Model!D30 -> N/A — insufficient comparable opening balance | C6: =Model!E30 -> 79.897168 | D6: =Model!F30 -> 80.313969 | E6: =Model!G30 -> 78.573363 | F6: =Model!H30 -> 87.338167 | G6: =Model!I30 -> 98.239314 | H6: =Model!J30 -> N/A — insufficient comparable disclosure | I6: =Model!K30 -> N/A — insufficient comparable disclosure | J6: Customer-side cash tie-up | K6: Pure DSO is the largest measured days component. It was about 79–80 days in FY2019–FY2021 and increased to 87 days in FY2022 and 98 days in FY2023; the change requires structural-break and peer context. | S6: =Model!F6 -> FY2020 | T6: =Model!F118 -> 1.1005308 | U6: =Model!F119 -> 2.5328189 | V6: =Model!F120 -> 4.3145127
A7: Contract Asset Days | B7: =Model!D31 -> 13.822891 | C7: =Model!E31 -> 12.620457 | D7: =Model!F31 -> 13.878343 | E7: =Model!G31 -> 14.80171 | F7: =Model!H31 -> 11.947375 | G7: =Model!I31 -> 11.439024 | H7: =Model!J31 -> 13.683681 | I7: =Model!K31 -> N/A — insufficient comparable disclosure | J7: Unbilled work | K7: Contract Asset Days stayed within a narrower range of about 11–15 days. The DSO increase was not matched by a comparable increase in unbilled work. | S7: =Model!G6 -> FY2021 | T7: =Model!G118 -> 0.78602178 | U7: =Model!G119 -> 1.4600875 | V7: =Model!G120 -> 2.0679271
A8: Days Inventory Outstanding (DIO) | B8: =Model!D32 -> N/A — opening balance not sufficiently comparable | C8: =Model!E32 -> 3.1254599 | D8: =Model!F32 -> 2.9681667 | E8: =Model!G32 -> 3.8822149 | F8: =Model!H32 -> 7.2241046 | G8: =Model!I32 -> 7.332627 | H8: =Model!J32 -> 5.8345731 | I8: =Model!K32 -> 6.4767759 | J8: Inventory | K8: DIO remained small relative to receivables, although it rose from roughly 3–4 days before FY2022 to about 7 days in FY2022–FY2023. | S8: =Model!H6 -> FY2022 | T8: =Model!H118 -> 0.7270842 | U8: =Model!H119 -> 1.3530933 | V8: =Model!H120 -> 2.1010241
A9: Days Payables Outstanding (DPO) | B9: =Model!D33 -> N/A — opening balance not sufficiently comparable | C9: =Model!E33 -> 30.487369 | D9: =Model!F33 -> 30.756619 | E9: =Model!G33 -> 30.999056 | F9: =Model!H33 -> 40.086851 | G9: =Model!I33 -> 49.431147 | H9: =Model!J33 -> N/A — insufficient comparable disclosure | I9: =Model!K33 -> N/A — insufficient comparable disclosure | J9: Supplier funding | K9: DPO increased from about 30–31 days through FY2021 to roughly 40 days in FY2022 and 49 days in FY2023, materially offsetting the rise in customer-side days. | S9: =Model!I6 -> FY2023 | T9: =Model!I118 -> 0.84340379 | U9: =Model!I119 -> 1.6113306 | V9: =Model!I120 -> 3.4271374
A10: Contract Liability Days | B10: =Model!D34 -> 36.486504 | C10: =Model!E34 -> 38.283483 | D10: =Model!F34 -> 41.476979 | E10: =Model!G34 -> 39.624984 | F10: =Model!H34 -> 37.944948 | G10: =Model!I34 -> 39.643285 | H10: =Model!J34 -> 39.439249 | I10: =Model!K34 -> N/A — insufficient comparable disclosure | J10: Customer advance funding | K10: Contract Liability Days remained broadly in the high-30s to low-40s, providing a substantial and relatively steady customer-funding offset. | S10: =Model!J6 -> FY2024 | T10: =Model!J118 -> 0.63798876 | U10: =Model!J119 -> 1.2262877 | V10: =Model!J120 -> 2.8518455
A11: Traditional CCC | B11: =Model!D93 -> N/A — incomplete comparable components | C11: =Model!E93 -> 52.535259 | D11: =Model!F93 -> 52.525517 | E11: =Model!G93 -> 51.456523 | F11: =Model!H93 -> 54.475421 | G11: =Model!I93 -> 56.140794 | H11: =Model!J93 -> N/A — incomplete comparable components | I11: =Model!K93 -> N/A — incomplete comparable components | J11: Overall operating cycle | K11: Traditional CCC rose modestly from about 51–53 days to 56 days by FY2023, while Adjusted CCC stayed broadly around 25–29 days because DPO and contract liabilities absorbed much of the tie-up.
A12: Adjusted CCC | B12: =Model!D94 -> N/A — incomplete comparable components | C12: =Model!E94 -> 26.872233 | D12: =Model!F94 -> 24.92688 | E12: =Model!G94 -> 26.633248 | F12: =Model!H94 -> 28.477847 | G12: =Model!I94 -> 27.936533 | H12: =Model!J94 -> N/A — incomplete comparable components | I12: =Model!K94 -> N/A — incomplete comparable components | J12: Profit-to-cash conversion | K12: Reported CFO exceeded Operating Profit and Net Income in all valid years. CFO / EBITDA ranged from about 64% to 110%, indicating positive but variable conversion, with FY2024 weaker on this measure. | S12: OWC CHART DATA — VALID YEARS ONLY
A13: Operating Working Capital (¥ million) | B13: =Model!D105 -> 222985 | C13: =Model!E105 -> 196585 | D13: =Model!F105 -> 209121 | E13: =Model!G105 -> 263737 | F13: =Model!H105 -> 446948 | G13: =Model!I105 -> 497249 | H13: =Model!J105 -> N/A — incomplete comparable operating working-capital components | I13: =Model!K105 -> N/A — incomplete comparable operating working-capital components | S13: Fiscal Year | T13: Operating Working Capital | U13: OWC / Revenue
A14: OWC / Revenue | B14: =Model!D107 -> 0.10306084 | C14: =Model!E107 -> 0.086723269 | D14: =Model!F107 -> 0.090190533 | E14: =Model!G107 -> 0.10334903 | F14: =Model!H107 -> 0.12805865 | G14: =Model!I107 -> 0.11385504 | H14: =Model!J107 -> N/A — incomplete comparable operating working-capital components | I14: =Model!K107 -> N/A — incomplete comparable operating working-capital components | S14: =Model!D6 -> FY2018 | T14: =Model!D105 -> 222985 | U14: =Model!D107 -> 0.10306084
A15: CFO / EBITDA | B15: =Model!D118 -> 0.7846952 | C15: =Model!E118 -> 0.94690565 | D15: =Model!F118 -> 1.1005308 | E15: =Model!G118 -> 0.78602178 | F15: =Model!H118 -> 0.7270842 | G15: =Model!I118 -> 0.84340379 | H15: =Model!J118 -> 0.63798876 | I15: =Model!K118 -> N/A — operating cash flow unavailable | S15: =Model!E6 -> FY2019 | T15: =Model!E105 -> 196585 | U15: =Model!E107 -> 0.086723269
A16: CFO / Operating Profit | B16: =Model!D119 -> 1.6382789 | C16: =Model!E119 -> 2.138433 | D16: =Model!F119 -> 2.5328189 | E16: =Model!G119 -> 1.4600875 | F16: =Model!H119 -> 1.3530933 | G16: =Model!I119 -> 1.6113306 | H16: =Model!J119 -> 1.2262877 | I16: =Model!K119 -> N/A — operating cash flow unavailable | S16: =Model!F6 -> FY2020 | T16: =Model!F105 -> 209121 | U16: =Model!F107 -> 0.090190533
A17: CFO / Net Income | B17: =Model!D120 -> 2.4768689 | C17: =Model!E120 -> 3.5100035 | D17: =Model!F120 -> 4.3145127 | E17: =Model!G120 -> 2.0679271 | F17: =Model!H120 -> 2.1010241 | G17: =Model!I120 -> 3.4271374 | H17: =Model!J120 -> 2.8518455 | I17: =Model!K120 -> N/A — operating cash flow unavailable | S17: =Model!G6 -> FY2021 | T17: =Model!G105 -> 263737 | U17: =Model!G107 -> 0.10334903
S18: =Model!H6 -> FY2022 | T18: =Model!H105 -> 446948 | U18: =Model!H107 -> 0.12805865
S19: =Model!I6 -> FY2023 | T19: =Model!I105 -> 497249 | U19: =Model!I107 -> 0.11385504
A20: COMPONENT BRIDGE — VALID COMPARABLE YEARS | S20: COMPONENT CHART DATA — VALID YEARS ONLY
A21: Fiscal Year | B21: DSO | C21: Contract Asset Days | D21: DIO | E21: DPO | F21: Contract Liability Days | G21: Traditional CCC | H21: Adjusted CCC | S21: Fiscal Year | T21: DSO | U21: Contract Asset Days | V21: DIO | W21: DPO (funding; negative) | X21: Contract Liability Days (funding; negative)
A22: =Model!E6 -> FY2019 | B22: =Model!E30 -> 79.897168 | C22: =Model!E31 -> 12.620457 | D22: =Model!E32 -> 3.1254599 | E22: =Model!E33 -> 30.487369 | F22: =Model!E34 -> 38.283483 | G22: =Model!E93 -> 52.535259 | H22: =Model!E94 -> 26.872233 | S22: =Model!E6 -> FY2019 | T22: =Model!E30 -> 79.897168 | U22: =Model!E31 -> 12.620457 | V22: =Model!E32 -> 3.1254599 | W22: =-Model!E33 -> -30.487369 | X22: =-Model!E34 -> -38.283483
A23: =Model!F6 -> FY2020 | B23: =Model!F30 -> 80.313969 | C23: =Model!F31 -> 13.878343 | D23: =Model!F32 -> 2.9681667 | E23: =Model!F33 -> 30.756619 | F23: =Model!F34 -> 41.476979 | G23: =Model!F93 -> 52.525517 | H23: =Model!F94 -> 24.92688 | S23: =Model!F6 -> FY2020 | T23: =Model!F30 -> 80.313969 | U23: =Model!F31 -> 13.878343 | V23: =Model!F32 -> 2.9681667 | W23: =-Model!F33 -> -30.756619 | X23: =-Model!F34 -> -41.476979
A24: =Model!G6 -> FY2021 | B24: =Model!G30 -> 78.573363 | C24: =Model!G31 -> 14.80171 | D24: =Model!G32 -> 3.8822149 | E24: =Model!G33 -> 30.999056 | F24: =Model!G34 -> 39.624984 | G24: =Model!G93 -> 51.456523 | H24: =Model!G94 -> 26.633248 | S24: =Model!G6 -> FY2021 | T24: =Model!G30 -> 78.573363 | U24: =Model!G31 -> 14.80171 | V24: =Model!G32 -> 3.8822149 | W24: =-Model!G33 -> -30.999056 | X24: =-Model!G34 -> -39.624984
A25: =Model!H6 -> FY2022 | B25: =Model!H30 -> 87.338167 | C25: =Model!H31 -> 11.947375 | D25: =Model!H32 -> 7.2241046 | E25: =Model!H33 -> 40.086851 | F25: =Model!H34 -> 37.944948 | G25: =Model!H93 -> 54.475421 | H25: =Model!H94 -> 28.477847 | S25: =Model!H6 -> FY2022 | T25: =Model!H30 -> 87.338167 | U25: =Model!H31 -> 11.947375 | V25: =Model!H32 -> 7.2241046 | W25: =-Model!H33 -> -40.086851 | X25: =-Model!H34 -> -37.944948
A26: =Model!I6 -> FY2023 | B26: =Model!I30 -> 98.239314 | C26: =Model!I31 -> 11.439024 | D26: =Model!I32 -> 7.332627 | E26: =Model!I33 -> 49.431147 | F26: =Model!I34 -> 39.643285 | G26: =Model!I93 -> 56.140794 | H26: =Model!I94 -> 27.936533 | S26: =Model!I6 -> FY2023 | T26: =Model!I30 -> 98.239314 | U26: =Model!I31 -> 11.439024 | V26: =Model!I32 -> 7.332627 | W26: =-Model!I33 -> -49.431147 | X26: =-Model!I34 -> -39.643285
A28: FY2022: structural break — NTT Ltd. combination | J28: FY2022: structural break — NTT Ltd. combination
A46: FY2022: structural break — NTT Ltd. combination | J46: FY2022: structural break — NTT Ltd. combination
A64: FY2022: structural break — NTT Ltd. combination
A84: C. COMPARABILITY WARNINGS / PHASE 2 LIMITATIONS | J84: D. PHASE 3 PRIORITIES
A85: Issue | C85: Affected period(s) | E85: Treatment / impact | J85: Rank | K85: Priority metric | N85: Why benchmark next
A86: JGAAP / IFRS boundary | C86: FY2017–FY2018 | E86: The main analysis begins in the IFRS era. FY2018 averages use an IFRS-restated opening bridge only for contract assets and total contract liabilities. | J86: 1 | K86: DSO | N86: Largest measured cash-tie-up component and the clearest post-FY2021 increase; peer context is needed before judging efficiency.
A87: NTT Ltd. structural break | C87: FY2022 | E87: The combination materially changed group scope. FY2022 averages span different scopes; no pro-forma adjustment is estimated. | J87: 2 | K87: OWC / Revenue | N87: Captures the overall year-end cash burden and increased around the FY2022 structural change.
A88: Pure trade AR / AP gaps | C88: FY2024–FY2025 | E88: Pure trade receivables and pure trade payables cannot be isolated reliably. DSO, DPO, CCC and OWC are unavailable rather than broadened. | J88: 3 | K88: Adjusted CCC | N88: Most economically complete operating-cycle measure because it includes unbilled work and customer advances.
A89: Contract-balance gaps | C89: FY2025 | E89: Separate contract assets and comparable total contract liabilities are unavailable. Current contract liabilities are not substituted. | J89: 4 | K89: CFO / EBITDA | N89: Reported conversion varied materially and weakened in FY2024, warranting cross-company context and one-off review.
A90: Reported CFO gap | C90: FY2025 | E90: Full-year operating cash flow is unavailable in the current database; cash-conversion ratios remain unavailable and CFO is not estimated. | J90: 5 | K90: DPO | N90: The supplier-funding offset rose sharply after FY2021; benchmarking can test whether this reflects normal terms or payment stretch.
A91: Shortened windows | C91: CCC FY2019–FY2023; OWC FY2018–FY2023 | E91: Shorter consistent series are used in preference to longer inconsistent series. | J91: 6 | K91: Contract Liability Days | N91: Customer advances are a meaningful funding source and should be compared using consistent total-liability definitions.
A92: Data-center transactions | C92: FY2024–FY2025 | E92: Held-for-sale and transfer/disposal effects can distort reported Operating Profit and EBITDA; ratios remain reported and unadjusted. | J92: 7 | K92: Contract Asset Days | N92: Unbilled work was comparatively stable, but peer comparison can test whether its 11–15 day range is structurally normal.
A93: Definition limitations | C93: All years | E93: Pure AR/AP and total contract-liability definitions are held constant. No combined captions, peer data, cash-release opportunity or financing savings are introduced. | J93: Phase 3 peer set: Accenture, Capgemini, CGI and TCS. No peer data are included in this Phase 2 workbook.
A96: PHASE 2 — NTT DATA STANDALONE DIAGNOSIS
A97: Diagnostic question | D97: Standalone conclusion
A98: 1. How did the operating working-capital profile change? | D98: Comparable OWC declined from 10.3% of revenue in FY2018 to 8.7% in FY2019, then rose to 10.3% in FY2021, 12.8% in FY2022 and 11.4% in FY2023. Absolute OWC also expanded. The FY2022 step-up is consistent with the enlarged NTT Ltd. scope as well as operating movements.
A99: 2. Where is capital tied up most heavily? | D99: Invoiced pure trade receivables are the dominant measured tie-up at roughly 79–98 days in the valid window. Contract assets add about 11–15 days, while inventory is much smaller at about 3–7 days.
A100: 3. What offsets these cash requirements? | D100: Supplier financing through DPO contributed about 30–49 days, and customer funding through Contract Liability Days contributed about 38–42 days. Together they substantially reduce the adjusted cycle relative to gross customer-side tie-up.
A101: 4. Does profit convert into operating cash consistently? | D101: Reported CFO exceeded Operating Profit and Net Income in every valid year, which is consistent with positive conversion. However, CFO / EBITDA ranged from about 64% to 110% and declined to 64% in FY2024, so conversion is not uniform and requires peer benchmarking and one-off review.
A102: 5. Which changes appear operational versus structural? | D102: Pre-FY2022 movements were comparatively modest. The FY2022 jump in balances, DSO, DIO, DPO and OWC coincides with the NTT Ltd. combination, so it cannot be attributed solely to execution. FY2023 may mix enlarged-scope normalization with operating change; FY2024–FY2025 data-center transactions further reduce profit comparability.
A103: 6. Strongest candidate for Phase 3 benchmarking? | D103: DSO currently appears the strongest first candidate because it is the largest tie-up component and increased materially in the valid post-FY2021 observations. OWC / Revenue and Adjusted CCC should follow so the receivables signal is assessed within the full funding structure.
A105: PHASE 2 CONCLUSION
A106: NTT DATA's standalone results suggest that receivables are the main measured use of operating cash, while supplier terms and customer advances provide meaningful offsets. The fully adjusted cycle remained comparatively contained through FY2023 despite higher DSO, but structural changes reduce like-for-like interpretation. Peer benchmarking—not a cash-release estimate—is the appropriate next analytical step.
