Workbook

Sheet A1 - Formula Library
A2: A1 — Formula Library | I2: =HYPERLINK("#'Home'!A1","← Back to Home") -> ← Back to Home
A3: Definitions and interpretation of every core working-capital and opportunity-sizing calculation
A4: =HYPERLINK("#'A8 - Sources'!A1","Source register ↗") -> Source register ↗
A6: Category | B6: Metric | C6: Formula | D6: Purpose | E6: Interpretation
A7: Balance convention | B7: Average Balance | C7: (Opening Balance + Closing Balance) ÷ 2 | D7: Used for days-based working-capital metrics. | E7: Smooths period-end movements when both endpoints exist.
A8: Receivables | B8: DSO | C8: Average Trade Receivables ÷ Revenue × 365 | D8: Measures receivables intensity. | E8: Days of Revenue represented by outstanding Trade Receivables.
A9: Project working capital | B9: Contract Asset Days | C9: Average Contract Assets ÷ Revenue × 365 | D9: Measures unbilled/project-stage capital absorption. | E9: Lower is generally favorable, subject to business mix.
A10: Inventory | B10: DIO | C10: Average Inventory ÷ Cost of Sales × 365 | D10: Measures inventory holding period. | E10: Used only where inventory and cost base are comparable.
A11: Payables | B11: DPO | C11: Average Trade Payables ÷ Cost of Sales × 365 | D11: Measures supplier funding. | E11: Higher days indicate more supplier financing, within sustainable terms.
A12: Customer funding | B12: Contract Liability Days | C12: Average Contract Liabilities ÷ Revenue × 365 | D12: Measures advance customer funding. | E12: Higher days indicate more customer funding, subject to contract mix.
A13: Cycle | B13: Traditional CCC | C13: DSO + DIO − DPO | D13: Conventional operating-cycle measure. | E13: Comparable only where DSO, DIO and DPO are all valid.
A14: Cycle | B14: Adjusted CCC | C14: DSO + Contract Asset Days + DIO − DPO − Contract Liability Days | D14: Adds project-stage capital absorption and customer funding. | E14: Captures contract-asset and contract-liability economics.
A15: Balance sheet | B15: Operating Working Capital | C15: Trade Receivables + Contract Assets + Inventory − Trade Payables − Contract Liabilities | D15: Measures net operating funding tied up. | E15: Uses closing balances—not average balances.
A16: Balance sheet | B16: OWC / Revenue | C16: Operating Working Capital ÷ Revenue | D16: Scales OWC to company activity. | E16: TCS reference only in the approved peer framework.
A17: Cash conversion | B17: Standardized EBITDA | C17: Operating Profit + Depreciation + Amortization | D17: Creates a consistent denominator. | E17: Official EBITDA KPIs are reference only where definitions differ.
... A29: Financing | B29: Realized Financing Benefit | C29: Cash Release × Financing Cost × Financing Utilization | D29: Sensitivity for less-than-full utilization. | E29: 75% reference is approximately ¥4.4bn/year.
A31: Important distinction: Cash release is a one-time balance-sheet effect; financing benefit is a potential recurring pre-tax effect if the lower financing requirement is maintained. No separate monetization of CCC, Adjusted CCC or OWC is included, avoiding double counting of the receivables opportunity.

Sheet A2 - Excel Implementation
A2: A2 — Excel Implementation | G2: =HYPERLINK("#'Home'!A1","← Back to Home") -> ← Back to Home
A3: Representative spreadsheet logic and audited function usage in the approved source workbooks
A4: =HYPERLINK("#'A8 - Sources'!A1","Source register ↗") -> Source register ↗
A6: Calculation | B6: Financial Logic | C6: Notes
A7: Average balance | B7: Mean of opening and closing balances | C7: Applied only when both endpoints are numeric.
A8: DSO | B8: Average AR ÷ Revenue × 365 | C8: Unavailable inputs remain N/A; no estimate.
A9: Contract Asset Days | B9: Average contract assets ÷ Revenue × 365 | C9: Same day-count convention as DSO.
A10: DIO | B10: Average inventory ÷ cost base × 365 | C10: Peer benchmark limited to TCS.
A11: DPO | B11: Average pure trade payables ÷ cost base × 365 | C11: CGI excluded because pure AP cannot be isolated.
A12: Contract Liability Days | B12: Average contract liabilities ÷ Revenue × 365 | C12: Current and non-current components combined where appropriate.
A13: Traditional CCC | B13: DSO + DIO − DPO | C13: Requires all three eligible inputs.
A14: Adjusted CCC | B14: DSO + CA Days + DIO − DPO − CL Days | C14: TCS reference only in peer work.
A15: Operating Working Capital | B15: Closing AR + CA + inventory − AP − CL | C15: Uses closing balances, not averages.
A16: OWC / Revenue | B16: OWC ÷ Revenue | C16: Unavailable inputs stay N/A.
A17: Standardized EBITDA | B17: Operating profit + D&A | C17: D&A is consistently assembled from available components.
... A27: Utilization sensitivity | B27: Benefit × utilization | C27: 75% realization reference only.

Sheet A3 - Peer Comparability
A2: A3 — Peer Comparability | H2: =HYPERLINK("#'Home'!A1","← Back to Home") -> ← Back to Home
A3: Final approved metric-by-metric peer eligibility; single-peer references are not industry medians
A4: =HYPERLINK("#'A8 - Sources'!A1","Source register ↗") -> Source register ↗
A6: Metric | B6: Accenture | C6: Capgemini | D6: CGI | E6: TCS | F6: Benchmark Type | G6: Notes
A7: DSO | B7: ✓ | C7: ✓ | D7: ✓ | E7: ✓ | F7: Multi-peer benchmark | G7: All four peers usable.
A8: Contract Asset Days | B8: ✓ | C8: ✓ | D8: ✓ | E8: ✓ | F8: Multi-peer benchmark | G8: All four peers usable; company-specific mapping rules applied.
A9: DIO | B9: — | C9: — | D9: — | E9: △ | F9: Single-peer reference | G9: TCS only; not labeled an industry median.
A10: DPO | B10: ✓ | C10: ✓ | D10: — | E10: ✓ | F10: Multi-peer benchmark | G10: CGI unavailable because pure Trade Payables cannot be isolated.
A11: Contract Liability Days | B11: ✓ | C11: ✓ | D11: ✓ | E11: ✓ | F11: Multi-peer benchmark | G11: All four peers usable.
A12: Traditional CCC | B12: — | C12: — | D12: — | E12: △ | F12: Single-peer reference | G12: TCS reference only because full component eligibility is required.
A13: Adjusted CCC | B13: — | C13: — | D13: — | E13: △ | F13: Single-peer reference | G13: TCS reference only.
A14: OWC / Revenue | B14: — | C14: — | D14: — | E14: △ | F14: Single-peer reference | G14: TCS reference only.
A15: CFO / Standardized EBITDA | B15: ✓ | C15: ✓ | D15: ✓ | E15: ✓ | F15: Multi-peer benchmark | G15: All four peers usable.
A16: CFO / Operating Profit | B16: ✓ | C16: ✓ | D16: ✓ | E16: ✓ | F16: Multi-peer benchmark | G16: All four peers usable.
A17: CFO / Net Income | B17: ✓ | C17: ✓ | D17: ✓ | E17: ✓ | F17: Multi-peer benchmark | G17: All four peers usable; attribution-basis caution retained.
A20: LEGEND AND BENCHMARK DISCIPLINE
A22: ✓ Comparable | B22: Approved for the stated metric and benchmark method.
A23: △ Comparable with adjustment | B23: Valid only in the limited TCS-only context shown; used as a single-peer reference.
A24: — Not comparable / unavailable | B24: Excluded for that metric; no value is estimated.

Sheet A4 - Normalization Rules
A2: A4 — Normalization Rules | F2: =HYPERLINK("#'Home'!A1","← Back to Home") -> ← Back to Home
A3: Material accounting, scope and availability treatments preserved from the approved comparability framework
A4: =HYPERLINK("#'A8 - Sources'!A1","Source register ↗") -> Source register ↗
A6: Company | B6: Raw Disclosure Issue | C6: Normalized Treatment | D6: Metrics Affected | E6: Reason
A7: TCS | B7: Billed AR, unbilled trade AR and true Contract Assets are separately disclosed. | C7: Normalized Trade Receivables = billed AR + unbilled trade AR; true Contract Assets remain separate. | D7: DSO; Contract Asset Days; CCC; OWC / Revenue | E7: Prevents unbilled trade receivables from being misclassified as Contract Assets.
A8: TCS | B8: Inventory is the only peer inventory series sufficiently comparable for the final framework. | C8: Retain TCS for DIO; treat DIO, CCC, Adjusted CCC and OWC / Revenue as single-peer references. | D8: DIO; Traditional CCC; Adjusted CCC; OWC / Revenue | E8: Avoids presenting a TCS-only reference as an industry median.
A9: CGI | B9: Pure Trade Payables and a compatible direct cost base cannot be isolated from broader payables/accruals. | C9: Set CGI DPO, CCC and OWC-based metrics to N/A; do not estimate pure Trade Payables. | D9: DPO; Traditional CCC; Adjusted CCC; OWC / Revenue | E9: Preserves denominator and balance-sheet purity.
A10: Capgemini | B10: WNS transaction changes comparability in FY2025. | C10: Exclude FY2025 from clean turnover metrics where required; use the approved clean window through FY2024. | D10: DSO; Contract Asset Days; DPO; Contract Liability Days; cash conversion | E10: Avoids mixing a structural transaction with operating trend.
A11: Accenture | B11: Acquisition-heavy periods and component disclosures require cautious aggregation. | C11: Use approved clean history through FY2025; combine current and non-current Contract Assets and deferred revenue where disclosed. | D11: Contract Asset Days; Contract Liability Days; cash conversion | E11: Keeps the balance definitions complete and consistent.
A12: NTT DATA | B12: JGAAP applies through FY2017; IFRS applies from FY2018. | C12: Use IFRS-based analytical history from FY2018 for the final peer work; retain earlier periods only in underlying source files. | D12: All historical metrics | E12: Avoids mixing accounting regimes in the final benchmark window.
A13: NTT DATA | B13: FY2019 includes IFRS 16 context. | C13: Retain FY2019 in approved clean periods; disclose context rather than excluding the year. | D13: All available FY2019 metrics | E13: Matches the final Phase 3 clean-window decision.
A14: NTT DATA | B14: NTT Ltd. was consolidated during FY2022. | C14: Flag FY2022 as a structural break and exclude it from clean-period summaries. | D14: All FY2022 metrics | E14: Prevents consolidation effects from distorting the baseline.
A15: NTT DATA | B15: Pure AR/AP are unavailable for FY2024 and FY2025; several FY2025 inputs are also unavailable. | C15: Report affected metrics as N/A; do not estimate AR, AP, CA, CL, CFO or D&A. | D15: DSO; DPO; CCC; Adjusted CCC; OWC / Revenue; CFO / Std EBITDA | E15: Preserves source integrity.
A16: NTT DATA | B16: FY2025 Revenue requires the approved opportunity-sizing normalization. | C16: Use normalized FY2025 Revenue of ¥4,875.1bn only in the Phase 4 DSO opportunity calculation. | D16: Cash release and financing benefit | E16: Does not create a new historical turnover observation.
A17: All companies | B17: Original reporting currencies and fiscal labels differ. | C17: Retain each company's source currency and unit; calculate ratios within company; do not convert currency for day/ratio metrics. | D17: All peer metrics | E17: Ratios are dimensionless; unnecessary FX conversion could add noise.
A18: All companies | B18: Days metrics require opening and closing balances. | C18: Use average balance only when both endpoints are available; otherwise return N/A—no invented opening balance. | D18: DSO; Contract Asset Days; DIO; DPO; Contract Liability Days | E18: Maintains consistent measurement and avoids unsupported estimates.
A20: Scope discipline: no new estimates, peers, scenarios, currencies, fiscal periods, targets or accounting reclassifications have been added. Missing or non-comparable items remain N/A. Structural events are flagged rather than normalized away.

Sheet A5 - NTT Historical Data
A2: A5 — NTT Historical Data | M2: =HYPERLINK("#'Home'!A1","← Back to Home") -> ← Back to Home
A3: Approved FY2018–FY2025 working-capital and cash-conversion dataset; unavailable values are never estimated
A4: =HYPERLINK("#'A8 - Sources'!A1","Source register ↗") -> Source register ↗
A6: FY | B6: DSO | C6: Contract Asset Days | D6: DIO | E6: DPO | F6: Contract Liability Days | G6: Traditional CCC | H6: Adjusted CCC | I6: OWC / Revenue | J6: CFO / Std EBITDA | L6: Structural Note
A7: FY2018 | B7: N/A | C7: 13.822891 | D7: N/A | E7: N/A | F7: 36.486504 | G7: N/A | H7: N/A | I7: 0.10306084 | J7: 0.79148597 | L7: IFRS basis from this period; clean observation where available.
A8: FY2019 | B8: 79.897168 | C8: 12.620457 | D8: 3.1254599 | E8: 30.487369 | F8: 38.283483 | G8: 52.535259 | H8: 26.872233 | I8: 0.086723269 | J8: 0.84817899 | L8: IFRS 16 context; retained in approved clean periods.
A9: FY2020 | B9: 80.313969 | C9: 13.878343 | D9: 2.9681667 | E9: 30.756619 | F9: 41.476979 | G9: 52.525517 | H9: 24.92688 | I9: 0.090190533 | J9: 0.99717961 | L9: Clean observation.
A10: FY2021 | B10: 78.573363 | C10: 14.80171 | D10: 3.8822149 | E10: 30.999056 | F10: 39.624984 | G10: 51.456523 | H10: 26.633248 | I10: 0.10334903 | J10: 0.71763974 | L10: Clean observation.
A11: FY2022 | B11: 87.338167 | C11: 11.947375 | D11: 7.2241046 | E11: 40.086851 | F11: 37.944948 | G11: 54.475421 | H11: 28.477847 | I11: 0.12805865 | J11: 0.65882194 | L11: FY2022 — Structural Break: NTT Ltd. consolidated during the year; excluded from clean summaries.
A12: FY2023 | B12: 98.239314 | C12: 11.439024 | D12: 7.332627 | E12: 49.431147 | F12: 39.643285 | G12: 56.140794 | H12: 27.936533 | I12: 0.11385504 | J12: 0.76608068 | L12: Clean observation; latest clean DSO and DPO.
A13: FY2024 | B13: N/A | C13: 13.683681 | D13: 5.8345731 | E13: N/A | F13: 39.439249 | G13: N/A | H13: N/A | I13: N/A | J13: 0.5772307 | L13: Data-center transaction caution; pure AR/AP unavailable; no estimate.
A14: FY2025 | B14: N/A | C14: N/A | D14: 6.4767759 | E14: N/A | F14: N/A | G14: N/A | H14: N/A | I14: N/A | J14: N/A | L14: Data-center caution; AR/AP/CA/CL/CFO/D&A unavailable; Revenue normalized only for opportunity sizing.
A17: APPROVED CLEAN-PERIOD SUMMARY STATISTICS
A19: Metric | B19: Latest Clean | C19: Clean Mean | D19: Clean Median | E19: Minimum | F19: Maximum | G19: Valid Observations
A20: DSO | B20: 98.239314 | C20: 84.255954 | D20: 80.105569 | E20: 78.573363 | F20: 98.239314 | G20: 4
A21: Contract Asset Days | B21: 13.683681 | C21: 13.374351 | D21: 13.753286 | E21: 11.439024 | F21: 14.80171 | G21: 6
A22: DIO | B22: 6.4767759 | C22: 4.9366363 | D22: 4.858394 | E22: 2.9681667 | F22: 7.332627 | G22: 6
A23: DPO | B23: 49.431147 | C23: 35.418548 | D23: 30.877837 | E23: 30.487369 | F23: 49.431147 | G23: 4
A24: Contract Liability Days | B24: 39.439249 | C24: 39.159081 | D24: 39.532117 | E24: 36.486504 | F24: 41.476979 | G24: 6
A25: Traditional CCC | B25: 56.140794 | C25: 53.164523 | D25: 52.530388 | E25: 51.456523 | F25: 56.140794 | G25: 4
A26: Adjusted CCC | B26: 27.936533 | C26: 26.592224 | D26: 26.752741 | E26: 24.92688 | F26: 27.936533 | G26: 4
A27: OWC / Revenue | B27: 0.11385504 | C27: 0.09943574 | D27: 0.10306084 | E27: 0.086723269 | F27: 0.11385504 | G27: 5
A28: CFO / Std EBITDA | B28: 0.5772307 | C28: 0.78296595 | D28: 0.77878332 | E28: 0.5772307 | F28: 0.99717961 | G28: 6
A30: Clean-period statistics reproduce the approved Phase 3 company summary. FY2022 is excluded as a structural break; availability windows vary by metric and no missing metric is replaced with zero.

Sheet A6 - Peer Benchmark Detail
A2: A6 — Peer Benchmark Detail | J2: =HYPERLINK("#'Home'!A1","← Back to Home") -> ← Back to Home
A3: Each peer is first summarized over its approved clean period; the benchmark is then the median of peer-company medians
A4: =HYPERLINK("#'A8 - Sources'!A1","Source register ↗") -> Source register ↗
A6: Metric | B6: Company | C6: Latest Clean | D6: Clean Median | E6: Clean Mean | F6: Minimum | G6: Maximum | H6: N | I6: Clean Window / Basis
A7: DSO | B7: NTT DATA | C7: 98.239314 | D7: 80.105569 | E7: 84.255954 | F7: 78.573363 | G7: 98.239314 | H7: 4 | I7: FY2019–FY2023
A8: DSO | B8: Accenture | C8: 65.32439 | D8: 60.276376 | E8: 60.785648 | F8: 57.128976 | G8: 65.32439 | H8: 5 | I8: FY2021–FY2025
A9: DSO | B9: Capgemini | C9: 54.190012 | D9: 54.190012 | E9: 55.344654 | F9: 53.758468 | G9: 58.86027 | H9: 5 | I9: FY2020–FY2024
A10: DSO | B10: CGI | C10: 28.224762 | D10: 28.235129 | E10: 28.407557 | F10: 27.740474 | G10: 28.999332 | H10: 5 | I10: FY2021–FY2025
A11: DSO | B11: TCS | C11: 86.870003 | D11: 78.806835 | E11: 79.256475 | F11: 74.723186 | G11: 86.870003 | H11: 5 | I11: FY2022–FY2026
A12: DSO | B12: Peer Median | C12: 59.757201 | D12: 57.233194 | E12: 55.377088 | F12: 28.235129 | G12: 78.806835 | H12: 4 | I12: Peer-company medians
A13: Contract Asset Days | B13: NTT DATA | C13: 13.683681 | D13: 13.753286 | E13: 13.374351 | F13: 11.439024 | G13: 14.80171 | H13: 6 | I13: FY2018–FY2024
A14: Contract Asset Days | B14: Accenture | C14: 10.50808 | D14: 8.491029 | E14: 8.3721052 | F14: 6.0224681 | G14: 10.50808 | H14: 5 | I14: FY2021–FY2025
A15: Contract Asset Days | B15: Capgemini | C15: 28.974022 | D15: 26.762367 | E15: 27.076574 | F15: 25.405286 | G15: 28.974022 | H15: 5 | I15: FY2020–FY2024
A16: Contract Asset Days | B16: CGI | C16: 29.544711 | D16: 29.814165 | E16: 30.447915 | F16: 29.244713 | G16: 31.909226 | H16: 5 | I16: FY2021–FY2025
A17: Contract Asset Days | B17: TCS | C17: 9.8924991 | D17: 9.0555236 | E17: 8.8807647 | F17: 8.0888404 | G17: 9.8924991 | H17: 5 | I17: FY2022–FY2026
A18: Contract Asset Days | B18: Peer Median | C18: 19.741051 | D18: 17.908946 | E18: 18.530771 | F18: 8.491029 | G18: 29.814165 | H18: 4 | I18: Peer-company medians
... A21: DPO | B21: Capgemini | C21: 36.161026 | D21: 36.743084 | E21: 37.06803 | F21: 35.992625 | G21: 38.730738 | H21: 5 | I21: FY2020–FY2024
A22: DPO | B22: CGI | C22: N/A | D22: N/A | E22: N/A | F22: N/A | G22: N/A | H22: 0 | I22: Unavailable
A23: DPO | B23: TCS | C23: 32.75758 | D23: 26.049096 | E23: 27.387378 | F23: 24.8569 | G23: 32.75758 | H23: 5 | I23: FY2022–FY2026
A24: DPO | B24: Peer Median | C24: 32.75758 | D24: 26.049096 | E24: 27.949611 | F24: 21.056652 | G24: 36.743084 | H24: 3 | I24: Peer-company medians
A25: Contract Liability Days | B25: NTT DATA | C25: 39.439249 | D25: 39.532117 | E25: 39.159081 | F25: 36.486504 | G25: 41.476979 | H25: 6 | I25: FY2018–FY2024
A26: Contract Liability Days | B26: Accenture | C26: 32.824878 | D26: 31.994415 | E26: 31.768322 | F26: 29.984974 | G26: 33.431155 | H26: 5 | I26: FY2021–FY2025
A27: Contract Liability Days | B27: Capgemini | C27: 22.498642 | D27: 22.705133 | E27: 23.063884 | F27: 21.649419 | G27: 24.611371 | H27: 5 | I27: FY2020–FY2024
A28: Contract Liability Days | B28: CGI | C28: 12.777143 | D28: 12.755355 | E28: 12.687956 | F28: 12.029429 | G28: 13.125009 | H28: 5 | I28: FY2021–FY2025
A29: Contract Liability Days | B29: TCS | C29: 6.615959 | D29: 6.7941368 | E29: 7.2996897 | F29: 6.1956964 | G29: 9.1290925 | H29: 5 | I29: FY2022–FY2026
A30: Contract Liability Days | B30: Peer Median | C30: 17.637893 | D30: 17.730244 | E30: 18.56226 | F30: 6.7941368 | G30: 31.994415 | H30: 4 | I30: Peer-company medians
A31: CFO / Std EBITDA | B31: NTT DATA | C31: 0.5772307 | D31: 0.77878332 | E31: 0.78296595 | F31: 0.5772307 | G31: 0.99717961 | H31: 6 | I31: FY2018–FY2024
A32: CFO / Std EBITDA | B32: Accenture | C32: 0.96172011 | D32: 0.93277838 | E32: 0.92853491 | F32: 0.82814429 | G32: 1.0264935 | H32: 5 | I32: FY2021–FY2025
A33: CFO / Std EBITDA | B33: Capgemini | C33: 0.83119447 | D33: 0.82895601 | E33: 0.85380628 | F33: 0.77219898 | G33: 1.0278773 | H33: 5 | I33: FY2020–FY2024
A34: CFO / Std EBITDA | B34: CGI | C34: 0.76804295 | D34: 0.76804295 | E34: 0.78363416 | F34: 0.73754283 | G34: 0.8672682 | H34: 5 | I34: FY2021–FY2025
... A36: CFO / Std EBITDA | B36: Peer Median | C36: 0.79961871 | D36: 0.79849948 | E36: 0.81383499 | F36: 0.72556263 | G36: 0.93277838 | H36: 4 | I36: Peer-company medians
A38: Benchmark method: (1) calculate each peer's clean-period median; (2) take the cross-sectional median of those peer-company medians. This gives each peer equal weight, regardless of the number of available annual observations.
A40: Metric | B40: NTT DATA | C40: Peer Benchmark | D40: Gap | E40: Interpretation
A41: DSO | B41: 80.105569 | C41: 57.233194 | D41: 22.872375 | E41: Clearest peer-relative weakness; NTT collection cycle is longer.
A42: Contract Asset Days | B42: 13.753286 | C42: 17.908946 | D42: -4.1556596 | E42: Relatively favorable versus peers.
A43: DPO | B43: 30.877837 | C43: 26.049096 | D43: 4.8287409 | E43: Modest supplier-funding advantage.
A44: Contract Liability Days | B44: 39.532117 | C44: 17.730244 | D44: 21.801873 | E44: Significant customer-funding advantage.
A45: CFO / Std EBITDA | B45: 0.77878332 | C45: 0.79849948 | D45: -0.019716157 | E45: Broadly near peers; approximately 2.0 percentage points lower.

Sheet A7 - Opportunity Bridge
A2: A7 — Opportunity Bridge | M2: =HYPERLINK("#'Home'!A1","← Back to Home") -> ← Back to Home
A3: Approved Phase 4 DSO-gap closure, cash-release and financing-benefit calculation
A4: =HYPERLINK("#'A8 - Sources'!A1","Source register ↗") -> Source register ↗
A5: BASE-CASE CALCULATION CHAIN | J5: APPROVED FINANCING-RATE INPUTS
A7: NTT DATA Baseline DSO | E7: ='A6 - Peer Benchmark Detail'!B41 -> 80.105569 | J7: Input | K7: Value | L7: Unit | M7: Source
A8: ↓ | J8: Interest expense | K8: 91722 | L8: ¥m | M8: Phase 4 — S3 Assumptions
A9: Peer Median DSO | E9: ='A6 - Peer Benchmark Detail'!C41 -> 57.233194 | J9: Opening interest-bearing debt | K9: 2175313 | L9: ¥m | M9: Phase 4 — S3 Assumptions
A10: ↓ | J10: Closing interest-bearing debt | K10: 2599077 | L10: ¥m | M10: Phase 4 — S3 Assumptions
A11: Observed Gap | E11: =E7-E9 -> 22.872375 | J11: Average debt | K11: =AVERAGE(K9,K10) -> 2387195 | L11: ¥m | M11: AVERAGE(opening, closing)
A12: ↓
A13: Base Gap Closure | E13: 0.5 | J13: Historical financing-cost proxy | K13: =K8/K11 -> 0.0384225 | M13: Interest expense ÷ average debt
A14: ↓ | J14: Approved normalized FY2025 Revenue | K14: 4875.1 | L14: ¥bn | M14: Phase 4 opportunity input
A15: DSO Improvement | E15: =E11*E13 -> 11.436188
A16: ↓
A17: Resulting DSO | E17: =E7-E15 -> 68.669381
A18: ↓
A19: Normalized FY2025 Revenue (¥bn) | E19: 4875.1
A20: ↓
A21: Potential Cash Release (¥bn) | E21: =E19*E15/365 -> 152.74673
A22: ↓
A23: Historical Financing-Cost Proxy | E23: =K13 -> 0.0384225
A24: ↓
A25: Potential Annual Pre-Tax Financing Benefit (¥bn/year) — 100% utilization | E25: =E21*E23 -> 5.8689114
A26: ↓
A27: 75% Financing-Utilization Reference (¥bn/year) | E27: =E25*75% -> 4.4016835
A30: APPROVED DSO OPPORTUNITY SCENARIOS
A32: Scenario | B32: Gap Closed | C32: DSO Improvement | D32: Resulting DSO | E32: Cash Release (¥bn) | F32: Financing Benefit — 100% Utilization (¥bn/year)
A33: Conservative | B33: 0.25 | C33: =$E$11*B33 -> 5.7180938 | D33: =$E$7-C33 -> 74.387475 | E33: =$E$19*C33/365 -> 76.373367 | F33: =E33*$K$13 -> 2.9344557
A34: Base | B34: 0.5 | C34: =$E$11*B34 -> 11.436188 | D34: =$E$7-C34 -> 68.669381 | E34: =$E$19*C34/365 -> 152.74673 | F34: =E34*$K$13 -> 5.8689114
A35: Upside | B35: 0.75 | C35: =$E$11*B35 -> 17.154281 | D35: =$E$7-C35 -> 62.951287 | E35: =$E$19*C35/365 -> 229.1201 | F35: =E35*$K$13 -> 8.8033671
A36: Full Convergence — Reference Only | B36: 1 | C36: =$E$11*B36 -> 22.872375 | D36: =$E$7-C36 -> 57.233194 | E36: =$E$19*C36/365 -> 305.49347 | F36: =E36*$K$13 -> 11.737823
A38: WARNING — ¥152.7bn is a one-time balance-sheet cash release and should not be added to the annual financing benefit. The ¥5.9bn/year figure is a potential recurring pre-tax benefit at 100% financing utilization; approximately ¥4.4bn/year is the 75% utilization reference. Full convergence is reference only.

Sheet A8 - Sources
A2: A8 — Sources | J2: =HYPERLINK("#'Home'!A1","← Back to Home") -> ← Back to Home
A3: Consolidated source register preserving approved document titles, fiscal years, locations, URLs and supported workbook metrics
A6: ID | B6: Company | C6: Metric / Data Item | D6: Fiscal Year | E6: Source Document | F6: Source Location / Page | G6: Source URL if available | H6: Used In | I6: Notes
A7: NTT-S01 | B7: NTT DATA | C7: All NTT historical inputs and updates | D7: FY2015–FY2026 | E7: NTT DATA Data Tables | F7: Data Tables page | G7: https://www.nttdata.com/global/en/investors/performance/fb | H7: A4; A5; A6; A7 | I7: Official IR data archive | Official IR | JGAAP through FY2017; IFRS from FY2018; updated after results.
A8: NTT-S02 | B8: NTT DATA | C8: FY2015–FY2016 financial inputs | D8: FY2015–FY2016 | E8: Annual Report 2017 | F8: Financial statements / notes | G8: https://www.nttdata.com/global/en/-/media/nttdataglobal/files/investors/inv004_financials/annual-report/fy2017_ar_b.pdf?rev=b1cb8171510c438d93f85170ef462b95 | H8: A4; A5; A6; A7 | I8: Annual report / audited financial statements | Audited | Primary source for FY2015 and FY2016 JGAAP.
A9: NTT-S03 | B9: NTT DATA | C9: FY2016–FY2017 financial inputs | D9: FY2016–FY2017 | E9: Annual Report 2018 | F9: Financial Information; historical highlights | G9: https://www.nttdata.com/global/en/-/media/nttdataglobal/files/investors/inv004_financials/annual-report/fy2018_ar_b.pdf?rev=6133c7d3db8942d8a5b0c640965b5fed | H9: A4; A5; A6; A7 | I9: Annual report / audited financial statements | Audited | Primary source for FY2016–FY2017 JGAAP and historical KPI values.
A10: NTT-S04 | B10: NTT DATA | C10: Historical KPIs and structural context | D10: FY2017–FY2022 | E10: Integrated Report 2022 | F10: Historical financial / non-financial data | G10: https://www.nttdata.com/global/en/-/media/nttdataglobal/1_files/investors/integrated-report/fy2022_ar_b.pdf | H10: A4; A5; A6; A7 | I10: Integrated report / historical financial data | Audited financial data + management report | Orders, backlog, capex, EBITDA, overseas sales and rating history.
A11: NTT-S05 | B11: NTT DATA | C11: FY2018 financial and working-capital inputs | D11: FY2018 | E11: Integrated Report / Annual Report 2019 | F11: Consolidated statements / notes | G11: https://www.nttdata.com/global/en/-/media/nttdataglobal/1_files/investors/integrated-report/fy2019_ar_b.pdf?rev=cf6cd677f4d3420094b591b4c92b6af4 | H11: A4; A5; A6; A7 | I11: Audited IFRS report | Audited | IFRS statement-of-position and working-capital breakdown.
A12: NTT-S06 | B12: NTT DATA | C12: FY2019 financial inputs | D12: FY2019 | E12: FY2019 Financial Results | F12: Consolidated statements | G12: https://www.nttdata.com/global/en/-/media/nttdataglobal/1_files/investors/financial-results/2019/fy2019_fs_4q_01.pdf | H12: A4; A5; A6; A7 | I12: Kessan Tanshin / final results | Official; Kessan Tanshin | FY2019 income and balance data.
A13: NTT-S07 | B13: NTT DATA | C13: FY2020 financial and working-capital inputs | D13: FY2020 | E13: Integrated Report 2020 | F13: Financial statements / management resources | G13: https://www.nttdata.com/global/en/-/media/nttdataglobal/1_files/investors/integrated-report/fy2020_ar_b.pdf?rev=3eb817c598a641959792e94610b81324 | H13: A4; A5; A6; A7 | I13: Audited IFRS report | Audited | FY2020 IFRS and rating information.
A14: NTT-S08 | B14: NTT DATA | C14: FY2021 financial and working-capital inputs | D14: FY2021 | E14: Integrated Report 2021 | F14: Financial statements / management resources | G14: https://www.nttdata.com/global/en/-/media/nttdataglobal/1_files/investors/integrated-report/fy2021_ar_b.pdf?rev=7b868a5c0f1a4c50b7eb6bce7f4c80e1 | H14: A4; A5; A6; A7 | I14: Audited IFRS report | Audited | FY2021 IFRS and rating context.
A15: NTT-S09 | B15: NTT DATA | C15: FY2022 financial inputs | D15: FY2022 | E15: FY2022 Financial Results | F15: Consolidated statements | G15: https://www.nttdata.com/global/en/-/media/nttdataglobal/1_files/investors/financial-results/2022/fy2022_fs_4q.pdf | H15: A4; A5; A6; A7 | I15: Kessan Tanshin / final results | Official; Kessan Tanshin | FY2022 statement figures.
A16: NTT-S10 | B16: NTT DATA | C16: FY2023 financial inputs | D16: FY2023 | E16: FY2023 Financial Results | F16: Consolidated statements | G16: https://www.nttdata.com/global/en/-/media/nttdataglobal/1_files/investors/financial-results/2023/fy2023_fs_4q.pdf?rev=362f0f5a70cf43628c53baadd69caee6 | H16: A4; A5; A6; A7 | I16: Kessan Tanshin / final results | Official; Kessan Tanshin | FY2023 statement figures / FY2022 comparison.
A17: NTT-S11 | B17: NTT DATA | C17: FY2024 financial, CFO, interest and debt inputs | D17: FY2024 | E17: FY2024 Financial Results | F17: Consolidated statements / cash flow | G17: https://www.nttdata.com/global/en/-/media/nttdataglobal/1_files/investors/financial-results/2024/fy2024_fs_4q.pdf | H17: A4; A5; A6; A7 | I17: Kessan Tanshin / final results | Official; Kessan Tanshin | Exact FY2024 statement and cash-flow values.
... A66: TR-040 | B66: NTT DATA | C66: Phase 3 standardized EBITDA only | D66: FY2024 | E66: NTT DATA FY2024 — Approved financial source | F66: FY2024 financial results, cash-flow statement p.20; official Kessan Tanshin (unaudited) | G66: https://www.nttdata.com/global/en/-/media/nttdataglobal/1_files/investors/financial-results/2024/fy2024_fs_4q.pdf?rev=27cf18c7761443188c7fa59817333d13 | H66: A5; A6; A7 | I66: Units: JPY / JPY million | Source file: Official NTT DATA filing

Sheet A9 - QA
A2: A9 — QA | E2: =HYPERLINK("#'Home'!A1","← Back to Home") -> ← Back to Home
A3: Formal audit of data reconciliation, formulas, analytical discipline, navigation and rendered presentation
A4: =HYPERLINK("#'A8 - Sources'!A1","Source register ↗") -> Source register ↗
A6: Review Area | B6: Test | C6: Result | D6: Notes
A7: Formula accuracy | B7: Core arithmetic and approved formulas recalculate within tolerance | C7: =IF(AND(ABS('A7 - Opportunity Bridge'!E11-22.8723750076781)<0.0000001,ABS('A7 - Opportunity Bridge'!E15-11.436187503839)<0.0000001),"PASS","FAIL") -> PASS | D7: Formula-linked opportunity and reconciliation checks.
A8: NTT historical data reconciliation | B8: Approved FY2018–FY2025 values match Phase 3 Step 4 | C8: =IF(AND(ABS('A5 - NTT Historical Data'!B8-79.8971681765725)<0.0000001,ABS('A5 - NTT Historical Data'!B12-98.2393144917087)<0.0000001),"PASS","FAIL") -> PASS | D8: Includes clean-window treatment.
A9: Peer raw-data reconciliation | B9: Source register reconciles to approved peer raw-data traceability | C9: PASS | D9: Audited against normalized peer source register.
A10: Normalized peer-data reconciliation | B10: Normalization rules match approved Phase 3 Step 3 | C10: PASS | D10: No new reclassification introduced.
A11: Metric eligibility consistency | B11: Multi-peer and single-peer eligibility counts match final framework | C11: =IF(AND(COUNTIF('A3 - Peer Comparability'!F7:F17,"Multi-peer benchmark")=7,COUNTIF('A3 - Peer Comparability'!F7:F17,"Single-peer reference")=4),"PASS","FAIL") -> PASS | D11: Seven multi-peer metrics; four single-peer references.
A12: Peer benchmark reconciliation | B12: NTT and peer benchmark values match approved Step 4 | C12: =IF(AND(ABS('A6 - Peer Benchmark Detail'!B41-80.1055687535538)<0.0000001,ABS('A6 - Peer Benchmark Detail'!C41-57.2331937458758)<0.0000001),"PASS","FAIL") -> PASS | D12: Company-median then cross-sectional-median method.
A13: DSO gap reconciliation | B13: Baseline less peer median equals approved 22.8724-day gap | C13: =IF(ABS('A7 - Opportunity Bridge'!E11-22.8723750076781)<0.0000001,"PASS","FAIL") -> PASS | D13: Direct formula check.
A14: Scenario reconciliation | B14: 25% / 50% / 75% / 100% scenarios reproduce Phase 4 | C14: =IF(AND(ABS('A7 - Opportunity Bridge'!C34-11.436187503839)<0.0000001,ABS('A7 - Opportunity Bridge'!D36-57.2331937458758)<0.0000001),"PASS","FAIL") -> PASS | D14: Full convergence remains reference only.
A15: Cash-release reconciliation | B15: Base cash release equals approved ¥152.7467bn | C15: =IF(ABS('A7 - Opportunity Bridge'!E34-152.746733424563)<0.0000001,"PASS","FAIL") -> PASS | D15: Revenue × DSO improvement ÷ 365.
A16: Financing-cost reconciliation | B16: Interest expense ÷ average debt equals approved 3.84225% | C16: =IF(ABS('A7 - Opportunity Bridge'!K13-0.0384225000471264)<0.0000001,"PASS","FAIL") -> PASS | D16: Uses approved FY2024 inputs.
A17: Financing-benefit reconciliation | B17: Base annual benefit equals approved ¥5.8689bn | C17: =IF(ABS('A7 - Opportunity Bridge'!F34-5.8689113722037)<0.0000001,"PASS","FAIL") -> PASS | D17: 100% financing-utilization reference.
A18: Structural-break treatment | B18: FY2022 is clearly flagged and excluded from clean summaries | C18: =IF(ISNUMBER(SEARCH("Structural Break",'A5 - NTT Historical Data'!L11)),"PASS","FAIL") -> PASS | D18: NTT Ltd. consolidation.
A19: N/A treatment | B19: Unavailable data are shown as N/A, not zero | C19: =IF(COUNTIF('A5 - NTT Historical Data'!B7:J14,"N/A")>0,"PASS","FAIL") -> PASS | D19: No unsupported estimates.
A20: No unsupported estimates | B20: No missing peer or NTT values have been imputed | C20: PASS | D20: Confirmed through workbook construction and source audit.
A21: No double counting | B21: CCC, Adjusted CCC and OWC are not monetized separately | C21: PASS | D21: Receivables opportunity is the only monetized lever.
A22: Cash release ≠ profit | B22: One-time release is explicitly separated from recurring benefit | C22: PASS | D22: Warning box included on A7.
A23: Full convergence marked reference only | B23: 100% scenario is visibly de-emphasized and labeled | C23: =IF(ISNUMBER(SEARCH("Reference Only",'A7 - Opportunity Bridge'!A36)),"PASS","FAIL") -> PASS | D23: Not presented as the base target.
A24: Source traceability | B24: Major conclusions have source-register support | C24: =IF(COUNTIF('A8 - Sources'!A7:A200,"<>")>=40,"PASS","FAIL") -> PASS | D24: NTT primary register plus peer input-source index.
A25: Formula-error scan | B25: No Excel calculation errors identified | C25: PASS | D25: Checked after workbook build and export against the standard error-token set.
A26: Visual review | B26: Every sheet rendered and inspected at normal scale | C26: PASS | D26: All ten sheets reviewed for readability and clipping.
A30: QA scope: source reconciliation, formulas, clean-period logic, structural-break and N/A treatment, peer eligibility, opportunity scenarios, one-time versus recurring benefit distinction, no-double-counting discipline, navigation, formula-error scanning and rendered visual inspection.
